[
  {
    "timestamp": "2025-03-04T08:00:00.000Z",
    "metadata": {
      "deviceId": "device-123",
      "data": 0,
      "timestamp": 1741075200000
    }
  },
  {
    "timestamp": "2025-03-04T08:01:12.000Z",
    "metadata": {
      "deviceId": "device-123",
      "data": 0,
      "timestamp": 1741075272000
    }
  },
  {
    "timestamp": "2025-03-04T08:02:22.000Z",
    "metadata": {
      "deviceId": "device-123",
      "data": 0,
      "timestamp": 1741075342000
    }
  },
  {
    "timestamp": "2025-03-04T08:03:42.000Z",
    "metadata": {
      "deviceId": "device-123",
      "data": 1,
      "timestamp": 1741075422000
    }
  },
  {
    "timestamp": "2025-03-04T08:05:17.000Z",
    "metadata": {
      "deviceId": "device-123",
      "data": 0,
      "timestamp": 1741075517000
    }
  },
  {
    "timestamp": "2025-03-04T08:07:17.000Z",
    "metadata": {
      "deviceId": "device-123",
      "data": 0,
      "timestamp": 1741075637000
    }
  },
  {
    "timestamp": "2025-03-04T08:08:59.000Z",
    "metadata": {
      "deviceId": "device-123",
      "data": 1,
      "timestamp": 1741075739000
    }
  },
  {
    "timestamp": "2025-03-04T08:10:33.000Z",
    "metadata": {
      "deviceId": "device-123",
      "data": 0,
      "timestamp": 1741075833000
    }
  },
  {
    "timestamp": "2025-03-04T08:12:10.000Z",
    "metadata": {
      "deviceId": "device-123",
      "data": 1,
      "timestamp": 1741075930000
    }
  },
  {
    "timestamp": "2025-03-04T08:13:52.000Z",
    "metadata": {
      "deviceId": "device-123",
      "data": 1,
      "timestamp": 1741076032000
    }
  },
  {
    "timestamp": "2025-03-04T08:15:46.000Z",
    "metadata": {
      "deviceId": "device-123",
      "data": 0,
      "timestamp": 1741076146000
    }
  },
  {
    "timestamp": "2025-03-04T08:17:05.000Z",
    "metadata": {
      "deviceId": "device-123",
      "data": 1,
      "timestamp": 1741076225000
    }
  },
  {
    "timestamp": "2025-03-04T08:18:57.000Z",
    "metadata": {
      "deviceId": "device-123",
      "data": 1,
      "timestamp": 1741076337000
    }
  },
  {
    "timestamp": "2025-03-04T08:20:29.000Z",
    "metadata": {
      "deviceId": "device-123",
      "data": 0,
      "timestamp": 1741076429000
    }
  },
  {
    "timestamp": "2025-03-04T08:22:11.000Z",
    "metadata": {
      "deviceId": "device-123",
      "data": 1,
      "timestamp": 1741076531000
    }
  },
  {
    "timestamp": "2025-03-04T08:23:59.000Z",
    "metadata": {
      "deviceId": "device-123",
      "data": 0,
      "timestamp": 1741076639000
    }
  },
  {
    "timestamp": "2025-03-04T08:25:44.000Z",
    "metadata": {
      "deviceId": "device-123",
      "data": 1,
      "timestamp": 1741076744000
    }
  },
  {
    "timestamp": "2025-03-04T08:27:32.000Z",
    "metadata": {
      "deviceId": "device-123",
      "data": 1,
      "timestamp": 1741076852000
    }
  },
  {
    "timestamp": "2025-03-04T08:28:50.000Z",
    "metadata": {
      "deviceId": "device-123",
      "data": 0,
      "timestamp": 1741076930000
    }
  },
  {
    "timestamp": "2025-03-04T08:29:59.000Z",
    "metadata": {
      "deviceId": "device-123",
      "data": 1,
      "timestamp": 1741076999000
    }
  },
  {
    "timestamp": "2025-03-04T08:31:50.000Z",
    "metadata": {
      "deviceId": "device-123",
      "data": 0,
      "timestamp": 1741077110000
    }
  },
  {
    "timestamp": "2025-03-04T08:33:50.000Z",
    "metadata": {
      "deviceId": "device-123",
      "data": 1,
      "timestamp": 1741077230000
    }
  },
  {
    "timestamp": "2025-03-04T08:35:45.000Z",
    "metadata": {
      "deviceId": "device-123",
      "data": 1,
      "timestamp": 1741077345000
    }
  },
  {
    "timestamp": "2025-03-04T08:36:45.000Z",
    "metadata": {
      "deviceId": "device-123",
      "data": 1,
      "timestamp": 1741077405000
    }
  },
  {
    "timestamp": "2025-03-04T08:38:12.000Z",
    "metadata": {
      "deviceId": "device-123",
      "data": 1,
      "timestamp": 1741077492000
    }
  },
  {
    "timestamp": "2025-03-04T08:40:09.000Z",
    "metadata": {
      "deviceId": "device-123",
      "data": 0,
      "timestamp": 1741077609000
    }
  },
  {
    "timestamp": "2025-03-04T08:41:17.000Z",
    "metadata": {
      "deviceId": "device-123",
      "data": 1,
      "timestamp": 1741077677000
    }
  },
  {
    "timestamp": "2025-03-04T08:43:02.000Z",
    "metadata": {
      "deviceId": "device-123",
      "data": 1,
      "timestamp": 1741077782000
    }
  },
  {
    "timestamp": "2025-03-04T08:44:28.000Z",
    "metadata": {
      "deviceId": "device-123",
      "data": 0,
      "timestamp": 1741077868000
    }
  },
  {
    "timestamp": "2025-03-04T08:45:41.000Z",
    "metadata": {
      "deviceId": "device-123",
      "data": 0,
      "timestamp": 1741077941000
    }
  },
  {
    "timestamp": "2025-03-04T08:47:40.000Z",
    "metadata": {
      "deviceId": "device-123",
      "data": 0,
      "timestamp": 1741078060000
    }
  },
  {
    "timestamp": "2025-03-04T08:49:27.000Z",
    "metadata": {
      "deviceId": "device-123",
      "data": 1,
      "timestamp": 1741078167000
    }
  },
  {
    "timestamp": "2025-03-04T08:51:07.000Z",
    "metadata": {
      "deviceId": "device-123",
      "data": 1,
      "timestamp": 1741078267000
    }
  },
  {
    "timestamp": "2025-03-04T08:52:58.000Z",
    "metadata": {
      "deviceId": "device-123",
      "data": 1,
      "timestamp": 1741078378000
    }
  },
  {
    "timestamp": "2025-03-04T08:54:32.000Z",
    "metadata": {
      "deviceId": "device-123",
      "data": 0,
      "timestamp": 1741078472000
    }
  },
  {
    "timestamp": "2025-03-04T08:56:25.000Z",
    "metadata": {
      "deviceId": "device-123",
      "data": 0,
      "timestamp": 1741078585000
    }
  },
  {
    "timestamp": "2025-03-04T08:57:53.000Z",
    "metadata": {
      "deviceId": "device-123",
      "data": 0,
      "timestamp": 1741078673000
    }
  },
  {
    "timestamp": "2025-03-04T08:59:31.000Z",
    "metadata": {
      "deviceId": "device-123",
      "data": 0,
      "timestamp": 1741078771000
    }
  },
  {
    "timestamp": "2025-03-04T09:00:44.000Z",
    "metadata": {
      "deviceId": "device-123",
      "data": 1,
      "timestamp": 1741078844000
    }
  },
  {
    "timestamp": "2025-03-04T09:02:01.000Z",
    "metadata": {
      "deviceId": "device-123",
      "data": 1,
      "timestamp": 1741078921000
    }
  },
  {
    "timestamp": "2025-03-04T09:03:03.000Z",
    "metadata": {
      "deviceId": "device-123",
      "data": 1,
      "timestamp": 1741078983000
    }
  },
  {
    "timestamp": "2025-03-04T09:04:39.000Z",
    "metadata": {
      "deviceId": "device-123",
      "data": 1,
      "timestamp": 1741079079000
    }
  },
  {
    "timestamp": "2025-03-04T09:06:01.000Z",
    "metadata": {
      "deviceId": "device-123",
      "data": 1,
      "timestamp": 1741079161000
    }
  },
  {
    "timestamp": "2025-03-04T09:07:31.000Z",
    "metadata": {
      "deviceId": "device-123",
      "data": 0,
      "timestamp": 1741079251000
    }
  },
  {
    "timestamp": "2025-03-04T09:09:28.000Z",
    "metadata": {
      "deviceId": "device-123",
      "data": 1,
      "timestamp": 1741079368000
    }
  },
  {
    "timestamp": "2025-03-04T09:10:45.000Z",
    "metadata": {
      "deviceId": "device-123",
      "data": 1,
      "timestamp": 1741079445000
    }
  },
  {
    "timestamp": "2025-03-04T09:11:55.000Z",
    "metadata": {
      "deviceId": "device-123",
      "data": 0,
      "timestamp": 1741079515000
    }
  },
  {
    "timestamp": "2025-03-04T09:13:43.000Z",
    "metadata": {
      "deviceId": "device-123",
      "data": 1,
      "timestamp": 1741079623000
    }
  },
  {
    "timestamp": "2025-03-04T09:15:30.000Z",
    "metadata": {
      "deviceId": "device-123",
      "data": 1,
      "timestamp": 1741079730000
    }
  },
  {
    "timestamp": "2025-03-04T09:16:44.000Z",
    "metadata": {
      "deviceId": "device-123",
      "data": 1,
      "timestamp": 1741079804000
    }
  },
  {
    "timestamp": "2025-03-04T09:18:10.000Z",
    "metadata": {
      "deviceId": "device-123",
      "data": 0,
      "timestamp": 1741079890000
    }
  },
  {
    "timestamp": "2025-03-04T09:19:41.000Z",
    "metadata": {
      "deviceId": "device-123",
      "data": 1,
      "timestamp": 1741079981000
    }
  },
  {
    "timestamp": "2025-03-04T09:21:22.000Z",
    "metadata": {
      "deviceId": "device-123",
      "data": 0,
      "timestamp": 1741080082000
    }
  },
  {
    "timestamp": "2025-03-04T09:22:22.000Z",
    "metadata": {
      "deviceId": "device-123",
      "data": 1,
      "timestamp": 1741080142000
    }
  },
  {
    "timestamp": "2025-03-04T09:24:21.000Z",
    "metadata": {
      "deviceId": "device-123",
      "data": 1,
      "timestamp": 1741080261000
    }
  },
  {
    "timestamp": "2025-03-04T09:26:03.000Z",
    "metadata": {
      "deviceId": "device-123",
      "data": 0,
      "timestamp": 1741080363000
    }
  },
  {
    "timestamp": "2025-03-04T09:27:03.000Z",
    "metadata": {
      "deviceId": "device-123",
      "data": 0,
      "timestamp": 1741080423000
    }
  },
  {
    "timestamp": "2025-03-04T09:28:26.000Z",
    "metadata": {
      "deviceId": "device-123",
      "data": 1,
      "timestamp": 1741080506000
    }
  },
  {
    "timestamp": "2025-03-04T09:30:06.000Z",
    "metadata": {
      "deviceId": "device-123",
      "data": 0,
      "timestamp": 1741080606000
    }
  },
  {
    "timestamp": "2025-03-04T09:31:13.000Z",
    "metadata": {
      "deviceId": "device-123",
      "data": 1,
      "timestamp": 1741080673000
    }
  },
  {
    "timestamp": "2025-03-04T09:32:33.000Z",
    "metadata": {
      "deviceId": "device-123",
      "data": 0,
      "timestamp": 1741080753000
    }
  },
  {
    "timestamp": "2025-03-04T09:34:19.000Z",
    "metadata": {
      "deviceId": "device-123",
      "data": 1,
      "timestamp": 1741080859000
    }
  },
  {
    "timestamp": "2025-03-04T09:35:57.000Z",
    "metadata": {
      "deviceId": "device-123",
      "data": 0,
      "timestamp": 1741080957000
    }
  },
  {
    "timestamp": "2025-03-04T09:37:57.000Z",
    "metadata": {
      "deviceId": "device-123",
      "data": 1,
      "timestamp": 1741081077000
    }
  },
  {
    "timestamp": "2025-03-04T09:39:47.000Z",
    "metadata": {
      "deviceId": "device-123",
      "data": 1,
      "timestamp": 1741081187000
    }
  },
  {
    "timestamp": "2025-03-04T09:40:51.000Z",
    "metadata": {
      "deviceId": "device-123",
      "data": 1,
      "timestamp": 1741081251000
    }
  },
  {
    "timestamp": "2025-03-04T09:42:47.000Z",
    "metadata": {
      "deviceId": "device-123",
      "data": 1,
      "timestamp": 1741081367000
    }
  },
  {
    "timestamp": "2025-03-04T09:44:28.000Z",
    "metadata": {
      "deviceId": "device-123",
      "data": 1,
      "timestamp": 1741081468000
    }
  },
  {
    "timestamp": "2025-03-04T09:46:25.000Z",
    "metadata": {
      "deviceId": "device-123",
      "data": 1,
      "timestamp": 1741081585000
    }
  },
  {
    "timestamp": "2025-03-04T09:47:56.000Z",
    "metadata": {
      "deviceId": "device-123",
      "data": 0,
      "timestamp": 1741081676000
    }
  },
  {
    "timestamp": "2025-03-04T09:49:32.000Z",
    "metadata": {
      "deviceId": "device-123",
      "data": 0,
      "timestamp": 1741081772000
    }
  },
  {
    "timestamp": "2025-03-04T09:51:20.000Z",
    "metadata": {
      "deviceId": "device-123",
      "data": 1,
      "timestamp": 1741081880000
    }
  },
  {
    "timestamp": "2025-03-04T09:52:28.000Z",
    "metadata": {
      "deviceId": "device-123",
      "data": 0,
      "timestamp": 1741081948000
    }
  },
  {
    "timestamp": "2025-03-04T09:54:14.000Z",
    "metadata": {
      "deviceId": "device-123",
      "data": 0,
      "timestamp": 1741082054000
    }
  },
  {
    "timestamp": "2025-03-04T09:55:49.000Z",
    "metadata": {
      "deviceId": "device-123",
      "data": 0,
      "timestamp": 1741082149000
    }
  },
  {
    "timestamp": "2025-03-04T09:57:20.000Z",
    "metadata": {
      "deviceId": "device-123",
      "data": 0,
      "timestamp": 1741082240000
    }
  },
  {
    "timestamp": "2025-03-04T09:59:08.000Z",
    "metadata": {
      "deviceId": "device-123",
      "data": 1,
      "timestamp": 1741082348000
    }
  },
  {
    "timestamp": "2025-03-04T10:00:54.000Z",
    "metadata": {
      "deviceId": "device-123",
      "data": 1,
      "timestamp": 1741082454000
    }
  },
  {
    "timestamp": "2025-03-04T10:02:52.000Z",
    "metadata": {
      "deviceId": "device-123",
      "data": 0,
      "timestamp": 1741082572000
    }
  },
  {
    "timestamp": "2025-03-04T10:04:17.000Z",
    "metadata": {
      "deviceId": "device-123",
      "data": 0,
      "timestamp": 1741082657000
    }
  },
  {
    "timestamp": "2025-03-04T10:06:11.000Z",
    "metadata": {
      "deviceId": "device-123",
      "data": 0,
      "timestamp": 1741082771000
    }
  },
  {
    "timestamp": "2025-03-04T10:07:16.000Z",
    "metadata": {
      "deviceId": "device-123",
      "data": 1,
      "timestamp": 1741082836000
    }
  },
  {
    "timestamp": "2025-03-04T10:09:07.000Z",
    "metadata": {
      "deviceId": "device-123",
      "data": 1,
      "timestamp": 1741082947000
    }
  },
  {
    "timestamp": "2025-03-04T10:11:07.000Z",
    "metadata": {
      "deviceId": "device-123",
      "data": 1,
      "timestamp": 1741083067000
    }
  },
  {
    "timestamp": "2025-03-04T10:12:48.000Z",
    "metadata": {
      "deviceId": "device-123",
      "data": 1,
      "timestamp": 1741083168000
    }
  },
  {
    "timestamp": "2025-03-04T10:14:45.000Z",
    "metadata": {
      "deviceId": "device-123",
      "data": 1,
      "timestamp": 1741083285000
    }
  },
  {
    "timestamp": "2025-03-04T10:16:14.000Z",
    "metadata": {
      "deviceId": "device-123",
      "data": 1,
      "timestamp": 1741083374000
    }
  },
  {
    "timestamp": "2025-03-04T10:17:40.000Z",
    "metadata": {
      "deviceId": "device-123",
      "data": 0,
      "timestamp": 1741083460000
    }
  },
  {
    "timestamp": "2025-03-04T10:19:22.000Z",
    "metadata": {
      "deviceId": "device-123",
      "data": 1,
      "timestamp": 1741083562000
    }
  },
  {
    "timestamp": "2025-03-04T10:21:15.000Z",
    "metadata": {
      "deviceId": "device-123",
      "data": 1,
      "timestamp": 1741083675000
    }
  },
  {
    "timestamp": "2025-03-04T10:22:34.000Z",
    "metadata": {
      "deviceId": "device-123",
      "data": 1,
      "timestamp": 1741083754000
    }
  },
  {
    "timestamp": "2025-03-04T10:23:57.000Z",
    "metadata": {
      "deviceId": "device-123",
      "data": 0,
      "timestamp": 1741083837000
    }
  },
  {
    "timestamp": "2025-03-04T10:25:29.000Z",
    "metadata": {
      "deviceId": "device-123",
      "data": 1,
      "timestamp": 1741083929000
    }
  },
  {
    "timestamp": "2025-03-04T10:27:15.000Z",
    "metadata": {
      "deviceId": "device-123",
      "data": 1,
      "timestamp": 1741084035000
    }
  },
  {
    "timestamp": "2025-03-04T10:29:04.000Z",
    "metadata": {
      "deviceId": "device-123",
      "data": 1,
      "timestamp": 1741084144000
    }
  },
  {
    "timestamp": "2025-03-04T10:30:58.000Z",
    "metadata": {
      "deviceId": "device-123",
      "data": 0,
      "timestamp": 1741084258000
    }
  },
  {
    "timestamp": "2025-03-04T10:32:12.000Z",
    "metadata": {
      "deviceId": "device-123",
      "data": 0,
      "timestamp": 1741084332000
    }
  },
  {
    "timestamp": "2025-03-04T10:34:04.000Z",
    "metadata": {
      "deviceId": "device-123",
      "data": 0,
      "timestamp": 1741084444000
    }
  },
  {
    "timestamp": "2025-03-04T10:36:02.000Z",
    "metadata": {
      "deviceId": "device-123",
      "data": 1,
      "timestamp": 1741084562000
    }
  },
  {
    "timestamp": "2025-03-04T10:37:14.000Z",
    "metadata": {
      "deviceId": "device-123",
      "data": 0,
      "timestamp": 1741084634000
    }
  },
  {
    "timestamp": "2025-03-04T10:39:12.000Z",
    "metadata": {
      "deviceId": "device-123",
      "data": 1,
      "timestamp": 1741084752000
    }
  },
  {
    "timestamp": "2025-03-04T10:40:12.000Z",
    "metadata": {
      "deviceId": "device-123",
      "data": 0,
      "timestamp": 1741084812000
    }
  },
  {
    "timestamp": "2025-03-04T10:41:38.000Z",
    "metadata": {
      "deviceId": "device-123",
      "data": 0,
      "timestamp": 1741084898000
    }
  },
  {
    "timestamp": "2025-03-04T10:42:39.000Z",
    "metadata": {
      "deviceId": "device-123",
      "data": 1,
      "timestamp": 1741084959000
    }
  },
  {
    "timestamp": "2025-03-04T10:44:18.000Z",
    "metadata": {
      "deviceId": "device-123",
      "data": 0,
      "timestamp": 1741085058000
    }
  },
  {
    "timestamp": "2025-03-04T10:45:53.000Z",
    "metadata": {
      "deviceId": "device-123",
      "data": 1,
      "timestamp": 1741085153000
    }
  },
  {
    "timestamp": "2025-03-04T10:47:15.000Z",
    "metadata": {
      "deviceId": "device-123",
      "data": 0,
      "timestamp": 1741085235000
    }
  },
  {
    "timestamp": "2025-03-04T10:49:02.000Z",
    "metadata": {
      "deviceId": "device-123",
      "data": 0,
      "timestamp": 1741085342000
    }
  },
  {
    "timestamp": "2025-03-04T10:50:50.000Z",
    "metadata": {
      "deviceId": "device-123",
      "data": 1,
      "timestamp": 1741085450000
    }
  },
  {
    "timestamp": "2025-03-04T10:52:00.000Z",
    "metadata": {
      "deviceId": "device-123",
      "data": 0,
      "timestamp": 1741085520000
    }
  },
  {
    "timestamp": "2025-03-04T10:53:28.000Z",
    "metadata": {
      "deviceId": "device-123",
      "data": 0,
      "timestamp": 1741085608000
    }
  },
  {
    "timestamp": "2025-03-04T10:55:05.000Z",
    "metadata": {
      "deviceId": "device-123",
      "data": 1,
      "timestamp": 1741085705000
    }
  },
  {
    "timestamp": "2025-03-04T10:56:26.000Z",
    "metadata": {
      "deviceId": "device-123",
      "data": 0,
      "timestamp": 1741085786000
    }
  },
  {
    "timestamp": "2025-03-04T10:57:53.000Z",
    "metadata": {
      "deviceId": "device-123",
      "data": 1,
      "timestamp": 1741085873000
    }
  },
  {
    "timestamp": "2025-03-04T10:59:28.000Z",
    "metadata": {
      "deviceId": "device-123",
      "data": 0,
      "timestamp": 1741085968000
    }
  },
  {
    "timestamp": "2025-03-04T11:01:01.000Z",
    "metadata": {
      "deviceId": "device-123",
      "data": 1,
      "timestamp": 1741086061000
    }
  },
  {
    "timestamp": "2025-03-04T11:02:42.000Z",
    "metadata": {
      "deviceId": "device-123",
      "data": 0,
      "timestamp": 1741086162000
    }
  },
  {
    "timestamp": "2025-03-04T11:04:10.000Z",
    "metadata": {
      "deviceId": "device-123",
      "data": 1,
      "timestamp": 1741086250000
    }
  },
  {
    "timestamp": "2025-03-04T11:05:54.000Z",
    "metadata": {
      "deviceId": "device-123",
      "data": 0,
      "timestamp": 1741086354000
    }
  },
  {
    "timestamp": "2025-03-04T11:07:39.000Z",
    "metadata": {
      "deviceId": "device-123",
      "data": 0,
      "timestamp": 1741086459000
    }
  },
  {
    "timestamp": "2025-03-04T11:08:42.000Z",
    "metadata": {
      "deviceId": "device-123",
      "data": 1,
      "timestamp": 1741086522000
    }
  },
  {
    "timestamp": "2025-03-04T11:10:08.000Z",
    "metadata": {
      "deviceId": "device-123",
      "data": 1,
      "timestamp": 1741086608000
    }
  },
  {
    "timestamp": "2025-03-04T11:11:43.000Z",
    "metadata": {
      "deviceId": "device-123",
      "data": 1,
      "timestamp": 1741086703000
    }
  },
  {
    "timestamp": "2025-03-04T11:13:19.000Z",
    "metadata": {
      "deviceId": "device-123",
      "data": 0,
      "timestamp": 1741086799000
    }
  },
  {
    "timestamp": "2025-03-04T11:15:16.000Z",
    "metadata": {
      "deviceId": "device-123",
      "data": 0,
      "timestamp": 1741086916000
    }
  },
  {
    "timestamp": "2025-03-04T11:17:04.000Z",
    "metadata": {
      "deviceId": "device-123",
      "data": 1,
      "timestamp": 1741087024000
    }
  },
  {
    "timestamp": "2025-03-04T11:18:13.000Z",
    "metadata": {
      "deviceId": "device-123",
      "data": 1,
      "timestamp": 1741087093000
    }
  },
  {
    "timestamp": "2025-03-04T11:19:19.000Z",
    "metadata": {
      "deviceId": "device-123",
      "data": 0,
      "timestamp": 1741087159000
    }
  },
  {
    "timestamp": "2025-03-04T11:20:40.000Z",
    "metadata": {
      "deviceId": "device-123",
      "data": 1,
      "timestamp": 1741087240000
    }
  },
  {
    "timestamp": "2025-03-04T11:22:16.000Z",
    "metadata": {
      "deviceId": "device-123",
      "data": 1,
      "timestamp": 1741087336000
    }
  },
  {
    "timestamp": "2025-03-04T11:23:44.000Z",
    "metadata": {
      "deviceId": "device-123",
      "data": 0,
      "timestamp": 1741087424000
    }
  },
  {
    "timestamp": "2025-03-04T11:24:53.000Z",
    "metadata": {
      "deviceId": "device-123",
      "data": 1,
      "timestamp": 1741087493000
    }
  },
  {
    "timestamp": "2025-03-04T11:26:36.000Z",
    "metadata": {
      "deviceId": "device-123",
      "data": 1,
      "timestamp": 1741087596000
    }
  },
  {
    "timestamp": "2025-03-04T11:28:27.000Z",
    "metadata": {
      "deviceId": "device-123",
      "data": 1,
      "timestamp": 1741087707000
    }
  },
  {
    "timestamp": "2025-03-04T11:29:35.000Z",
    "metadata": {
      "deviceId": "device-123",
      "data": 0,
      "timestamp": 1741087775000
    }
  },
  {
    "timestamp": "2025-03-04T11:31:00.000Z",
    "metadata": {
      "deviceId": "device-123",
      "data": 0,
      "timestamp": 1741087860000
    }
  },
  {
    "timestamp": "2025-03-04T11:32:56.000Z",
    "metadata": {
      "deviceId": "device-123",
      "data": 1,
      "timestamp": 1741087976000
    }
  },
  {
    "timestamp": "2025-03-04T11:34:31.000Z",
    "metadata": {
      "deviceId": "device-123",
      "data": 1,
      "timestamp": 1741088071000
    }
  },
  {
    "timestamp": "2025-03-04T11:36:02.000Z",
    "metadata": {
      "deviceId": "device-123",
      "data": 0,
      "timestamp": 1741088162000
    }
  },
  {
    "timestamp": "2025-03-04T11:37:34.000Z",
    "metadata": {
      "deviceId": "device-123",
      "data": 0,
      "timestamp": 1741088254000
    }
  },
  {
    "timestamp": "2025-03-04T11:39:22.000Z",
    "metadata": {
      "deviceId": "device-123",
      "data": 0,
      "timestamp": 1741088362000
    }
  },
  {
    "timestamp": "2025-03-04T11:41:09.000Z",
    "metadata": {
      "deviceId": "device-123",
      "data": 1,
      "timestamp": 1741088469000
    }
  },
  {
    "timestamp": "2025-03-04T11:42:24.000Z",
    "metadata": {
      "deviceId": "device-123",
      "data": 1,
      "timestamp": 1741088544000
    }
  },
  {
    "timestamp": "2025-03-04T11:43:39.000Z",
    "metadata": {
      "deviceId": "device-123",
      "data": 0,
      "timestamp": 1741088619000
    }
  },
  {
    "timestamp": "2025-03-04T11:44:41.000Z",
    "metadata": {
      "deviceId": "device-123",
      "data": 1,
      "timestamp": 1741088681000
    }
  },
  {
    "timestamp": "2025-03-04T11:46:28.000Z",
    "metadata": {
      "deviceId": "device-123",
      "data": 1,
      "timestamp": 1741088788000
    }
  },
  {
    "timestamp": "2025-03-04T11:48:28.000Z",
    "metadata": {
      "deviceId": "device-123",
      "data": 1,
      "timestamp": 1741088908000
    }
  },
  {
    "timestamp": "2025-03-04T11:49:54.000Z",
    "metadata": {
      "deviceId": "device-123",
      "data": 1,
      "timestamp": 1741088994000
    }
  },
  {
    "timestamp": "2025-03-04T11:51:51.000Z",
    "metadata": {
      "deviceId": "device-123",
      "data": 1,
      "timestamp": 1741089111000
    }
  },
  {
    "timestamp": "2025-03-04T11:53:40.000Z",
    "metadata": {
      "deviceId": "device-123",
      "data": 1,
      "timestamp": 1741089220000
    }
  },
  {
    "timestamp": "2025-03-04T11:55:29.000Z",
    "metadata": {
      "deviceId": "device-123",
      "data": 1,
      "timestamp": 1741089329000
    }
  },
  {
    "timestamp": "2025-03-04T11:57:02.000Z",
    "metadata": {
      "deviceId": "device-123",
      "data": 0,
      "timestamp": 1741089422000
    }
  },
  {
    "timestamp": "2025-03-04T11:58:34.000Z",
    "metadata": {
      "deviceId": "device-123",
      "data": 0,
      "timestamp": 1741089514000
    }
  },
  {
    "timestamp": "2025-03-04T11:59:35.000Z",
    "metadata": {
      "deviceId": "device-123",
      "data": 1,
      "timestamp": 1741089575000
    }
  },
  {
    "timestamp": "2025-03-04T12:00:41.000Z",
    "metadata": {
      "deviceId": "device-123",
      "data": 0,
      "timestamp": 1741089641000
    }
  },
  {
    "timestamp": "2025-03-04T12:02:39.000Z",
    "metadata": {
      "deviceId": "device-123",
      "data": 1,
      "timestamp": 1741089759000
    }
  },
  {
    "timestamp": "2025-03-04T12:04:04.000Z",
    "metadata": {
      "deviceId": "device-123",
      "data": 1,
      "timestamp": 1741089844000
    }
  },
  {
    "timestamp": "2025-03-04T12:05:17.000Z",
    "metadata": {
      "deviceId": "device-123",
      "data": 0,
      "timestamp": 1741089917000
    }
  },
  {
    "timestamp": "2025-03-04T12:06:53.000Z",
    "metadata": {
      "deviceId": "device-123",
      "data": 0,
      "timestamp": 1741090013000
    }
  },
  {
    "timestamp": "2025-03-04T12:08:27.000Z",
    "metadata": {
      "deviceId": "device-123",
      "data": 1,
      "timestamp": 1741090107000
    }
  },
  {
    "timestamp": "2025-03-04T12:09:37.000Z",
    "metadata": {
      "deviceId": "device-123",
      "data": 0,
      "timestamp": 1741090177000
    }
  },
  {
    "timestamp": "2025-03-04T12:11:30.000Z",
    "metadata": {
      "deviceId": "device-123",
      "data": 0,
      "timestamp": 1741090290000
    }
  },
  {
    "timestamp": "2025-03-04T12:13:05.000Z",
    "metadata": {
      "deviceId": "device-123",
      "data": 1,
      "timestamp": 1741090385000
    }
  },
  {
    "timestamp": "2025-03-04T12:14:33.000Z",
    "metadata": {
      "deviceId": "device-123",
      "data": 0,
      "timestamp": 1741090473000
    }
  },
  {
    "timestamp": "2025-03-04T12:16:14.000Z",
    "metadata": {
      "deviceId": "device-123",
      "data": 0,
      "timestamp": 1741090574000
    }
  },
  {
    "timestamp": "2025-03-04T12:17:55.000Z",
    "metadata": {
      "deviceId": "device-123",
      "data": 1,
      "timestamp": 1741090675000
    }
  },
  {
    "timestamp": "2025-03-04T12:19:32.000Z",
    "metadata": {
      "deviceId": "device-123",
      "data": 1,
      "timestamp": 1741090772000
    }
  },
  {
    "timestamp": "2025-03-04T12:21:18.000Z",
    "metadata": {
      "deviceId": "device-123",
      "data": 0,
      "timestamp": 1741090878000
    }
  },
  {
    "timestamp": "2025-03-04T12:22:31.000Z",
    "metadata": {
      "deviceId": "device-123",
      "data": 1,
      "timestamp": 1741090951000
    }
  },
  {
    "timestamp": "2025-03-04T12:24:23.000Z",
    "metadata": {
      "deviceId": "device-123",
      "data": 0,
      "timestamp": 1741091063000
    }
  },
  {
    "timestamp": "2025-03-04T12:25:25.000Z",
    "metadata": {
      "deviceId": "device-123",
      "data": 0,
      "timestamp": 1741091125000
    }
  },
  {
    "timestamp": "2025-03-04T12:26:52.000Z",
    "metadata": {
      "deviceId": "device-123",
      "data": 1,
      "timestamp": 1741091212000
    }
  },
  {
    "timestamp": "2025-03-04T12:27:56.000Z",
    "metadata": {
      "deviceId": "device-123",
      "data": 1,
      "timestamp": 1741091276000
    }
  },
  {
    "timestamp": "2025-03-04T12:29:26.000Z",
    "metadata": {
      "deviceId": "device-123",
      "data": 0,
      "timestamp": 1741091366000
    }
  },
  {
    "timestamp": "2025-03-04T12:30:32.000Z",
    "metadata": {
      "deviceId": "device-123",
      "data": 1,
      "timestamp": 1741091432000
    }
  },
  {
    "timestamp": "2025-03-04T12:32:14.000Z",
    "metadata": {
      "deviceId": "device-123",
      "data": 1,
      "timestamp": 1741091534000
    }
  },
  {
    "timestamp": "2025-03-04T12:34:11.000Z",
    "metadata": {
      "deviceId": "device-123",
      "data": 1,
      "timestamp": 1741091651000
    }
  },
  {
    "timestamp": "2025-03-04T12:35:51.000Z",
    "metadata": {
      "deviceId": "device-123",
      "data": 0,
      "timestamp": 1741091751000
    }
  },
  {
    "timestamp": "2025-03-04T12:37:41.000Z",
    "metadata": {
      "deviceId": "device-123",
      "data": 1,
      "timestamp": 1741091861000
    }
  },
  {
    "timestamp": "2025-03-04T12:39:12.000Z",
    "metadata": {
      "deviceId": "device-123",
      "data": 1,
      "timestamp": 1741091952000
    }
  },
  {
    "timestamp": "2025-03-04T12:40:34.000Z",
    "metadata": {
      "deviceId": "device-123",
      "data": 1,
      "timestamp": 1741092034000
    }
  },
  {
    "timestamp": "2025-03-04T12:42:32.000Z",
    "metadata": {
      "deviceId": "device-123",
      "data": 0,
      "timestamp": 1741092152000
    }
  },
  {
    "timestamp": "2025-03-04T12:44:12.000Z",
    "metadata": {
      "deviceId": "device-123",
      "data": 1,
      "timestamp": 1741092252000
    }
  },
  {
    "timestamp": "2025-03-04T12:45:15.000Z",
    "metadata": {
      "deviceId": "device-123",
      "data": 0,
      "timestamp": 1741092315000
    }
  },
  {
    "timestamp": "2025-03-04T12:47:00.000Z",
    "metadata": {
      "deviceId": "device-123",
      "data": 0,
      "timestamp": 1741092420000
    }
  },
  {
    "timestamp": "2025-03-04T12:48:21.000Z",
    "metadata": {
      "deviceId": "device-123",
      "data": 1,
      "timestamp": 1741092501000
    }
  },
  {
    "timestamp": "2025-03-04T12:49:47.000Z",
    "metadata": {
      "deviceId": "device-123",
      "data": 1,
      "timestamp": 1741092587000
    }
  },
  {
    "timestamp": "2025-03-04T12:50:57.000Z",
    "metadata": {
      "deviceId": "device-123",
      "data": 1,
      "timestamp": 1741092657000
    }
  },
  {
    "timestamp": "2025-03-04T12:52:56.000Z",
    "metadata": {
      "deviceId": "device-123",
      "data": 0,
      "timestamp": 1741092776000
    }
  },
  {
    "timestamp": "2025-03-04T12:54:50.000Z",
    "metadata": {
      "deviceId": "device-123",
      "data": 1,
      "timestamp": 1741092890000
    }
  },
  {
    "timestamp": "2025-03-04T12:56:30.000Z",
    "metadata": {
      "deviceId": "device-123",
      "data": 0,
      "timestamp": 1741092990000
    }
  },
  {
    "timestamp": "2025-03-04T12:57:39.000Z",
    "metadata": {
      "deviceId": "device-123",
      "data": 0,
      "timestamp": 1741093059000
    }
  },
  {
    "timestamp": "2025-03-04T12:58:55.000Z",
    "metadata": {
      "deviceId": "device-123",
      "data": 0,
      "timestamp": 1741093135000
    }
  },
  {
    "timestamp": "2025-03-04T13:00:15.000Z",
    "metadata": {
      "deviceId": "device-123",
      "data": 0,
      "timestamp": 1741093215000
    }
  },
  {
    "timestamp": "2025-03-04T13:01:45.000Z",
    "metadata": {
      "deviceId": "device-123",
      "data": 0,
      "timestamp": 1741093305000
    }
  },
  {
    "timestamp": "2025-03-04T13:03:40.000Z",
    "metadata": {
      "deviceId": "device-123",
      "data": 0,
      "timestamp": 1741093420000
    }
  },
  {
    "timestamp": "2025-03-04T13:05:09.000Z",
    "metadata": {
      "deviceId": "device-123",
      "data": 1,
      "timestamp": 1741093509000
    }
  },
  {
    "timestamp": "2025-03-04T13:06:34.000Z",
    "metadata": {
      "deviceId": "device-123",
      "data": 0,
      "timestamp": 1741093594000
    }
  },
  {
    "timestamp": "2025-03-04T13:08:01.000Z",
    "metadata": {
      "deviceId": "device-123",
      "data": 0,
      "timestamp": 1741093681000
    }
  },
  {
    "timestamp": "2025-03-04T13:09:25.000Z",
    "metadata": {
      "deviceId": "device-123",
      "data": 0,
      "timestamp": 1741093765000
    }
  },
  {
    "timestamp": "2025-03-04T13:11:01.000Z",
    "metadata": {
      "deviceId": "device-123",
      "data": 0,
      "timestamp": 1741093861000
    }
  },
  {
    "timestamp": "2025-03-04T13:12:45.000Z",
    "metadata": {
      "deviceId": "device-123",
      "data": 1,
      "timestamp": 1741093965000
    }
  },
  {
    "timestamp": "2025-03-04T13:13:56.000Z",
    "metadata": {
      "deviceId": "device-123",
      "data": 0,
      "timestamp": 1741094036000
    }
  },
  {
    "timestamp": "2025-03-04T13:15:38.000Z",
    "metadata": {
      "deviceId": "device-123",
      "data": 0,
      "timestamp": 1741094138000
    }
  },
  {
    "timestamp": "2025-03-04T13:16:57.000Z",
    "metadata": {
      "deviceId": "device-123",
      "data": 0,
      "timestamp": 1741094217000
    }
  },
  {
    "timestamp": "2025-03-04T13:18:48.000Z",
    "metadata": {
      "deviceId": "device-123",
      "data": 1,
      "timestamp": 1741094328000
    }
  },
  {
    "timestamp": "2025-03-04T13:20:45.000Z",
    "metadata": {
      "deviceId": "device-123",
      "data": 0,
      "timestamp": 1741094445000
    }
  },
  {
    "timestamp": "2025-03-04T13:22:08.000Z",
    "metadata": {
      "deviceId": "device-123",
      "data": 1,
      "timestamp": 1741094528000
    }
  },
  {
    "timestamp": "2025-03-04T13:23:55.000Z",
    "metadata": {
      "deviceId": "device-123",
      "data": 1,
      "timestamp": 1741094635000
    }
  },
  {
    "timestamp": "2025-03-04T13:25:24.000Z",
    "metadata": {
      "deviceId": "device-123",
      "data": 0,
      "timestamp": 1741094724000
    }
  },
  {
    "timestamp": "2025-03-04T13:27:23.000Z",
    "metadata": {
      "deviceId": "device-123",
      "data": 0,
      "timestamp": 1741094843000
    }
  },
  {
    "timestamp": "2025-03-04T13:28:30.000Z",
    "metadata": {
      "deviceId": "device-123",
      "data": 0,
      "timestamp": 1741094910000
    }
  },
  {
    "timestamp": "2025-03-04T13:29:40.000Z",
    "metadata": {
      "deviceId": "device-123",
      "data": 1,
      "timestamp": 1741094980000
    }
  },
  {
    "timestamp": "2025-03-04T13:31:26.000Z",
    "metadata": {
      "deviceId": "device-123",
      "data": 1,
      "timestamp": 1741095086000
    }
  },
  {
    "timestamp": "2025-03-04T13:32:40.000Z",
    "metadata": {
      "deviceId": "device-123",
      "data": 0,
      "timestamp": 1741095160000
    }
  },
  {
    "timestamp": "2025-03-04T13:34:06.000Z",
    "metadata": {
      "deviceId": "device-123",
      "data": 0,
      "timestamp": 1741095246000
    }
  },
  {
    "timestamp": "2025-03-04T13:35:35.000Z",
    "metadata": {
      "deviceId": "device-123",
      "data": 0,
      "timestamp": 1741095335000
    }
  },
  {
    "timestamp": "2025-03-04T13:37:00.000Z",
    "metadata": {
      "deviceId": "device-123",
      "data": 0,
      "timestamp": 1741095420000
    }
  },
  {
    "timestamp": "2025-03-04T13:38:57.000Z",
    "metadata": {
      "deviceId": "device-123",
      "data": 0,
      "timestamp": 1741095537000
    }
  },
  {
    "timestamp": "2025-03-04T13:40:43.000Z",
    "metadata": {
      "deviceId": "device-123",
      "data": 1,
      "timestamp": 1741095643000
    }
  },
  {
    "timestamp": "2025-03-04T13:42:24.000Z",
    "metadata": {
      "deviceId": "device-123",
      "data": 1,
      "timestamp": 1741095744000
    }
  },
  {
    "timestamp": "2025-03-04T13:43:24.000Z",
    "metadata": {
      "deviceId": "device-123",
      "data": 1,
      "timestamp": 1741095804000
    }
  },
  {
    "timestamp": "2025-03-04T13:45:20.000Z",
    "metadata": {
      "deviceId": "device-123",
      "data": 0,
      "timestamp": 1741095920000
    }
  },
  {
    "timestamp": "2025-03-04T13:47:13.000Z",
    "metadata": {
      "deviceId": "device-123",
      "data": 0,
      "timestamp": 1741096033000
    }
  },
  {
    "timestamp": "2025-03-04T13:48:13.000Z",
    "metadata": {
      "deviceId": "device-123",
      "data": 1,
      "timestamp": 1741096093000
    }
  },
  {
    "timestamp": "2025-03-04T13:49:42.000Z",
    "metadata": {
      "deviceId": "device-123",
      "data": 1,
      "timestamp": 1741096182000
    }
  },
  {
    "timestamp": "2025-03-04T13:51:39.000Z",
    "metadata": {
      "deviceId": "device-123",
      "data": 1,
      "timestamp": 1741096299000
    }
  },
  {
    "timestamp": "2025-03-04T13:52:50.000Z",
    "metadata": {
      "deviceId": "device-123",
      "data": 1,
      "timestamp": 1741096370000
    }
  },
  {
    "timestamp": "2025-03-04T13:54:47.000Z",
    "metadata": {
      "deviceId": "device-123",
      "data": 1,
      "timestamp": 1741096487000
    }
  },
  {
    "timestamp": "2025-03-04T13:55:51.000Z",
    "metadata": {
      "deviceId": "device-123",
      "data": 0,
      "timestamp": 1741096551000
    }
  },
  {
    "timestamp": "2025-03-04T13:57:09.000Z",
    "metadata": {
      "deviceId": "device-123",
      "data": 1,
      "timestamp": 1741096629000
    }
  },
  {
    "timestamp": "2025-03-04T13:58:56.000Z",
    "metadata": {
      "deviceId": "device-123",
      "data": 0,
      "timestamp": 1741096736000
    }
  },
  {
    "timestamp": "2025-03-04T14:00:07.000Z",
    "metadata": {
      "deviceId": "device-123",
      "data": 0,
      "timestamp": 1741096807000
    }
  },
  {
    "timestamp": "2025-03-04T14:01:35.000Z",
    "metadata": {
      "deviceId": "device-123",
      "data": 0,
      "timestamp": 1741096895000
    }
  },
  {
    "timestamp": "2025-03-04T14:02:53.000Z",
    "metadata": {
      "deviceId": "device-123",
      "data": 0,
      "timestamp": 1741096973000
    }
  },
  {
    "timestamp": "2025-03-04T14:04:25.000Z",
    "metadata": {
      "deviceId": "device-123",
      "data": 0,
      "timestamp": 1741097065000
    }
  },
  {
    "timestamp": "2025-03-04T14:05:39.000Z",
    "metadata": {
      "deviceId": "device-123",
      "data": 0,
      "timestamp": 1741097139000
    }
  },
  {
    "timestamp": "2025-03-04T14:07:28.000Z",
    "metadata": {
      "deviceId": "device-123",
      "data": 1,
      "timestamp": 1741097248000
    }
  },
  {
    "timestamp": "2025-03-04T14:08:56.000Z",
    "metadata": {
      "deviceId": "device-123",
      "data": 1,
      "timestamp": 1741097336000
    }
  },
  {
    "timestamp": "2025-03-04T14:10:11.000Z",
    "metadata": {
      "deviceId": "device-123",
      "data": 0,
      "timestamp": 1741097411000
    }
  },
  {
    "timestamp": "2025-03-04T14:11:11.000Z",
    "metadata": {
      "deviceId": "device-123",
      "data": 1,
      "timestamp": 1741097471000
    }
  },
  {
    "timestamp": "2025-03-04T14:12:27.000Z",
    "metadata": {
      "deviceId": "device-123",
      "data": 0,
      "timestamp": 1741097547000
    }
  },
  {
    "timestamp": "2025-03-04T14:13:51.000Z",
    "metadata": {
      "deviceId": "device-123",
      "data": 1,
      "timestamp": 1741097631000
    }
  },
  {
    "timestamp": "2025-03-04T14:15:12.000Z",
    "metadata": {
      "deviceId": "device-123",
      "data": 1,
      "timestamp": 1741097712000
    }
  },
  {
    "timestamp": "2025-03-04T14:16:16.000Z",
    "metadata": {
      "deviceId": "device-123",
      "data": 0,
      "timestamp": 1741097776000
    }
  },
  {
    "timestamp": "2025-03-04T14:18:12.000Z",
    "metadata": {
      "deviceId": "device-123",
      "data": 0,
      "timestamp": 1741097892000
    }
  },
  {
    "timestamp": "2025-03-04T14:19:27.000Z",
    "metadata": {
      "deviceId": "device-123",
      "data": 0,
      "timestamp": 1741097967000
    }
  },
  {
    "timestamp": "2025-03-04T14:20:27.000Z",
    "metadata": {
      "deviceId": "device-123",
      "data": 1,
      "timestamp": 1741098027000
    }
  },
  {
    "timestamp": "2025-03-04T14:22:15.000Z",
    "metadata": {
      "deviceId": "device-123",
      "data": 1,
      "timestamp": 1741098135000
    }
  },
  {
    "timestamp": "2025-03-04T14:23:27.000Z",
    "metadata": {
      "deviceId": "device-123",
      "data": 0,
      "timestamp": 1741098207000
    }
  },
  {
    "timestamp": "2025-03-04T14:25:25.000Z",
    "metadata": {
      "deviceId": "device-123",
      "data": 0,
      "timestamp": 1741098325000
    }
  },
  {
    "timestamp": "2025-03-04T14:27:17.000Z",
    "metadata": {
      "deviceId": "device-123",
      "data": 1,
      "timestamp": 1741098437000
    }
  },
  {
    "timestamp": "2025-03-04T14:28:53.000Z",
    "metadata": {
      "deviceId": "device-123",
      "data": 0,
      "timestamp": 1741098533000
    }
  },
  {
    "timestamp": "2025-03-04T14:30:46.000Z",
    "metadata": {
      "deviceId": "device-123",
      "data": 1,
      "timestamp": 1741098646000
    }
  },
  {
    "timestamp": "2025-03-04T14:31:58.000Z",
    "metadata": {
      "deviceId": "device-123",
      "data": 1,
      "timestamp": 1741098718000
    }
  },
  {
    "timestamp": "2025-03-04T14:33:53.000Z",
    "metadata": {
      "deviceId": "device-123",
      "data": 1,
      "timestamp": 1741098833000
    }
  },
  {
    "timestamp": "2025-03-04T14:35:46.000Z",
    "metadata": {
      "deviceId": "device-123",
      "data": 0,
      "timestamp": 1741098946000
    }
  },
  {
    "timestamp": "2025-03-04T14:37:17.000Z",
    "metadata": {
      "deviceId": "device-123",
      "data": 1,
      "timestamp": 1741099037000
    }
  },
  {
    "timestamp": "2025-03-04T14:38:41.000Z",
    "metadata": {
      "deviceId": "device-123",
      "data": 0,
      "timestamp": 1741099121000
    }
  },
  {
    "timestamp": "2025-03-04T14:39:57.000Z",
    "metadata": {
      "deviceId": "device-123",
      "data": 1,
      "timestamp": 1741099197000
    }
  },
  {
    "timestamp": "2025-03-04T14:41:07.000Z",
    "metadata": {
      "deviceId": "device-123",
      "data": 0,
      "timestamp": 1741099267000
    }
  },
  {
    "timestamp": "2025-03-04T14:42:43.000Z",
    "metadata": {
      "deviceId": "device-123",
      "data": 1,
      "timestamp": 1741099363000
    }
  },
  {
    "timestamp": "2025-03-04T14:44:23.000Z",
    "metadata": {
      "deviceId": "device-123",
      "data": 0,
      "timestamp": 1741099463000
    }
  },
  {
    "timestamp": "2025-03-04T14:46:18.000Z",
    "metadata": {
      "deviceId": "device-123",
      "data": 0,
      "timestamp": 1741099578000
    }
  },
  {
    "timestamp": "2025-03-04T14:48:01.000Z",
    "metadata": {
      "deviceId": "device-123",
      "data": 1,
      "timestamp": 1741099681000
    }
  },
  {
    "timestamp": "2025-03-04T14:49:32.000Z",
    "metadata": {
      "deviceId": "device-123",
      "data": 0,
      "timestamp": 1741099772000
    }
  },
  {
    "timestamp": "2025-03-04T14:50:53.000Z",
    "metadata": {
      "deviceId": "device-123",
      "data": 1,
      "timestamp": 1741099853000
    }
  },
  {
    "timestamp": "2025-03-04T14:51:54.000Z",
    "metadata": {
      "deviceId": "device-123",
      "data": 0,
      "timestamp": 1741099914000
    }
  },
  {
    "timestamp": "2025-03-04T14:53:04.000Z",
    "metadata": {
      "deviceId": "device-123",
      "data": 1,
      "timestamp": 1741099984000
    }
  },
  {
    "timestamp": "2025-03-04T14:54:26.000Z",
    "metadata": {
      "deviceId": "device-123",
      "data": 0,
      "timestamp": 1741100066000
    }
  },
  {
    "timestamp": "2025-03-04T14:56:00.000Z",
    "metadata": {
      "deviceId": "device-123",
      "data": 0,
      "timestamp": 1741100160000
    }
  },
  {
    "timestamp": "2025-03-04T14:57:52.000Z",
    "metadata": {
      "deviceId": "device-123",
      "data": 0,
      "timestamp": 1741100272000
    }
  },
  {
    "timestamp": "2025-03-04T14:59:36.000Z",
    "metadata": {
      "deviceId": "device-123",
      "data": 1,
      "timestamp": 1741100376000
    }
  },
  {
    "timestamp": "2025-03-04T15:01:01.000Z",
    "metadata": {
      "deviceId": "device-123",
      "data": 0,
      "timestamp": 1741100461000
    }
  },
  {
    "timestamp": "2025-03-04T15:02:08.000Z",
    "metadata": {
      "deviceId": "device-123",
      "data": 1,
      "timestamp": 1741100528000
    }
  },
  {
    "timestamp": "2025-03-04T15:03:34.000Z",
    "metadata": {
      "deviceId": "device-123",
      "data": 1,
      "timestamp": 1741100614000
    }
  },
  {
    "timestamp": "2025-03-04T15:05:32.000Z",
    "metadata": {
      "deviceId": "device-123",
      "data": 0,
      "timestamp": 1741100732000
    }
  },
  {
    "timestamp": "2025-03-04T15:06:46.000Z",
    "metadata": {
      "deviceId": "device-123",
      "data": 1,
      "timestamp": 1741100806000
    }
  },
  {
    "timestamp": "2025-03-04T15:08:42.000Z",
    "metadata": {
      "deviceId": "device-123",
      "data": 1,
      "timestamp": 1741100922000
    }
  },
  {
    "timestamp": "2025-03-04T15:10:37.000Z",
    "metadata": {
      "deviceId": "device-123",
      "data": 1,
      "timestamp": 1741101037000
    }
  },
  {
    "timestamp": "2025-03-04T15:11:37.000Z",
    "metadata": {
      "deviceId": "device-123",
      "data": 0,
      "timestamp": 1741101097000
    }
  },
  {
    "timestamp": "2025-03-04T15:12:54.000Z",
    "metadata": {
      "deviceId": "device-123",
      "data": 0,
      "timestamp": 1741101174000
    }
  },
  {
    "timestamp": "2025-03-04T15:13:58.000Z",
    "metadata": {
      "deviceId": "device-123",
      "data": 1,
      "timestamp": 1741101238000
    }
  },
  {
    "timestamp": "2025-03-04T15:15:00.000Z",
    "metadata": {
      "deviceId": "device-123",
      "data": 1,
      "timestamp": 1741101300000
    }
  },
  {
    "timestamp": "2025-03-04T15:16:06.000Z",
    "metadata": {
      "deviceId": "device-123",
      "data": 1,
      "timestamp": 1741101366000
    }
  },
  {
    "timestamp": "2025-03-04T15:17:26.000Z",
    "metadata": {
      "deviceId": "device-123",
      "data": 0,
      "timestamp": 1741101446000
    }
  },
  {
    "timestamp": "2025-03-04T15:19:19.000Z",
    "metadata": {
      "deviceId": "device-123",
      "data": 1,
      "timestamp": 1741101559000
    }
  },
  {
    "timestamp": "2025-03-04T15:21:11.000Z",
    "metadata": {
      "deviceId": "device-123",
      "data": 1,
      "timestamp": 1741101671000
    }
  },
  {
    "timestamp": "2025-03-04T15:22:31.000Z",
    "metadata": {
      "deviceId": "device-123",
      "data": 0,
      "timestamp": 1741101751000
    }
  },
  {
    "timestamp": "2025-03-04T15:23:36.000Z",
    "metadata": {
      "deviceId": "device-123",
      "data": 0,
      "timestamp": 1741101816000
    }
  },
  {
    "timestamp": "2025-03-04T15:25:13.000Z",
    "metadata": {
      "deviceId": "device-123",
      "data": 1,
      "timestamp": 1741101913000
    }
  },
  {
    "timestamp": "2025-03-04T15:26:25.000Z",
    "metadata": {
      "deviceId": "device-123",
      "data": 0,
      "timestamp": 1741101985000
    }
  },
  {
    "timestamp": "2025-03-04T15:27:27.000Z",
    "metadata": {
      "deviceId": "device-123",
      "data": 0,
      "timestamp": 1741102047000
    }
  },
  {
    "timestamp": "2025-03-04T15:28:48.000Z",
    "metadata": {
      "deviceId": "device-123",
      "data": 1,
      "timestamp": 1741102128000
    }
  },
  {
    "timestamp": "2025-03-04T15:30:27.000Z",
    "metadata": {
      "deviceId": "device-123",
      "data": 0,
      "timestamp": 1741102227000
    }
  },
  {
    "timestamp": "2025-03-04T15:32:06.000Z",
    "metadata": {
      "deviceId": "device-123",
      "data": 1,
      "timestamp": 1741102326000
    }
  },
  {
    "timestamp": "2025-03-04T15:33:11.000Z",
    "metadata": {
      "deviceId": "device-123",
      "data": 1,
      "timestamp": 1741102391000
    }
  },
  {
    "timestamp": "2025-03-04T15:34:53.000Z",
    "metadata": {
      "deviceId": "device-123",
      "data": 0,
      "timestamp": 1741102493000
    }
  },
  {
    "timestamp": "2025-03-04T15:36:43.000Z",
    "metadata": {
      "deviceId": "device-123",
      "data": 1,
      "timestamp": 1741102603000
    }
  },
  {
    "timestamp": "2025-03-04T15:37:48.000Z",
    "metadata": {
      "deviceId": "device-123",
      "data": 1,
      "timestamp": 1741102668000
    }
  },
  {
    "timestamp": "2025-03-04T15:39:43.000Z",
    "metadata": {
      "deviceId": "device-123",
      "data": 0,
      "timestamp": 1741102783000
    }
  },
  {
    "timestamp": "2025-03-04T15:41:03.000Z",
    "metadata": {
      "deviceId": "device-123",
      "data": 1,
      "timestamp": 1741102863000
    }
  },
  {
    "timestamp": "2025-03-04T15:42:56.000Z",
    "metadata": {
      "deviceId": "device-123",
      "data": 1,
      "timestamp": 1741102976000
    }
  },
  {
    "timestamp": "2025-03-04T15:44:51.000Z",
    "metadata": {
      "deviceId": "device-123",
      "data": 0,
      "timestamp": 1741103091000
    }
  },
  {
    "timestamp": "2025-03-04T15:46:36.000Z",
    "metadata": {
      "deviceId": "device-123",
      "data": 0,
      "timestamp": 1741103196000
    }
  },
  {
    "timestamp": "2025-03-04T15:48:14.000Z",
    "metadata": {
      "deviceId": "device-123",
      "data": 0,
      "timestamp": 1741103294000
    }
  },
  {
    "timestamp": "2025-03-04T15:49:31.000Z",
    "metadata": {
      "deviceId": "device-123",
      "data": 0,
      "timestamp": 1741103371000
    }
  },
  {
    "timestamp": "2025-03-04T15:51:25.000Z",
    "metadata": {
      "deviceId": "device-123",
      "data": 0,
      "timestamp": 1741103485000
    }
  },
  {
    "timestamp": "2025-03-04T15:53:15.000Z",
    "metadata": {
      "deviceId": "device-123",
      "data": 0,
      "timestamp": 1741103595000
    }
  },
  {
    "timestamp": "2025-03-04T15:54:28.000Z",
    "metadata": {
      "deviceId": "device-123",
      "data": 1,
      "timestamp": 1741103668000
    }
  },
  {
    "timestamp": "2025-03-04T15:55:44.000Z",
    "metadata": {
      "deviceId": "device-123",
      "data": 1,
      "timestamp": 1741103744000
    }
  },
  {
    "timestamp": "2025-03-04T15:57:37.000Z",
    "metadata": {
      "deviceId": "device-123",
      "data": 1,
      "timestamp": 1741103857000
    }
  },
  {
    "timestamp": "2025-03-04T15:59:14.000Z",
    "metadata": {
      "deviceId": "device-123",
      "data": 0,
      "timestamp": 1741103954000
    }
  },
  {
    "timestamp": "2025-03-04T16:00:18.000Z",
    "metadata": {
      "deviceId": "device-123",
      "data": 1,
      "timestamp": 1741104018000
    }
  },
  {
    "timestamp": "2025-03-04T16:01:40.000Z",
    "metadata": {
      "deviceId": "device-123",
      "data": 0,
      "timestamp": 1741104100000
    }
  },
  {
    "timestamp": "2025-03-04T16:03:21.000Z",
    "metadata": {
      "deviceId": "device-123",
      "data": 0,
      "timestamp": 1741104201000
    }
  },
  {
    "timestamp": "2025-03-04T16:04:23.000Z",
    "metadata": {
      "deviceId": "device-123",
      "data": 1,
      "timestamp": 1741104263000
    }
  },
  {
    "timestamp": "2025-03-04T16:06:18.000Z",
    "metadata": {
      "deviceId": "device-123",
      "data": 0,
      "timestamp": 1741104378000
    }
  },
  {
    "timestamp": "2025-03-04T16:07:48.000Z",
    "metadata": {
      "deviceId": "device-123",
      "data": 1,
      "timestamp": 1741104468000
    }
  },
  {
    "timestamp": "2025-03-04T16:09:18.000Z",
    "metadata": {
      "deviceId": "device-123",
      "data": 0,
      "timestamp": 1741104558000
    }
  },
  {
    "timestamp": "2025-03-04T16:11:13.000Z",
    "metadata": {
      "deviceId": "device-123",
      "data": 1,
      "timestamp": 1741104673000
    }
  },
  {
    "timestamp": "2025-03-04T16:12:41.000Z",
    "metadata": {
      "deviceId": "device-123",
      "data": 0,
      "timestamp": 1741104761000
    }
  },
  {
    "timestamp": "2025-03-04T16:13:54.000Z",
    "metadata": {
      "deviceId": "device-123",
      "data": 1,
      "timestamp": 1741104834000
    }
  },
  {
    "timestamp": "2025-03-04T16:15:11.000Z",
    "metadata": {
      "deviceId": "device-123",
      "data": 0,
      "timestamp": 1741104911000
    }
  },
  {
    "timestamp": "2025-03-04T16:17:04.000Z",
    "metadata": {
      "deviceId": "device-123",
      "data": 1,
      "timestamp": 1741105024000
    }
  },
  {
    "timestamp": "2025-03-04T16:18:04.000Z",
    "metadata": {
      "deviceId": "device-123",
      "data": 0,
      "timestamp": 1741105084000
    }
  },
  {
    "timestamp": "2025-03-04T16:19:37.000Z",
    "metadata": {
      "deviceId": "device-123",
      "data": 0,
      "timestamp": 1741105177000
    }
  },
  {
    "timestamp": "2025-03-04T16:21:29.000Z",
    "metadata": {
      "deviceId": "device-123",
      "data": 0,
      "timestamp": 1741105289000
    }
  },
  {
    "timestamp": "2025-03-04T16:22:30.000Z",
    "metadata": {
      "deviceId": "device-123",
      "data": 0,
      "timestamp": 1741105350000
    }
  },
  {
    "timestamp": "2025-03-04T16:24:25.000Z",
    "metadata": {
      "deviceId": "device-123",
      "data": 0,
      "timestamp": 1741105465000
    }
  },
  {
    "timestamp": "2025-03-04T16:25:34.000Z",
    "metadata": {
      "deviceId": "device-123",
      "data": 1,
      "timestamp": 1741105534000
    }
  },
  {
    "timestamp": "2025-03-04T16:27:00.000Z",
    "metadata": {
      "deviceId": "device-123",
      "data": 1,
      "timestamp": 1741105620000
    }
  },
  {
    "timestamp": "2025-03-04T16:28:35.000Z",
    "metadata": {
      "deviceId": "device-123",
      "data": 0,
      "timestamp": 1741105715000
    }
  },
  {
    "timestamp": "2025-03-04T16:30:04.000Z",
    "metadata": {
      "deviceId": "device-123",
      "data": 0,
      "timestamp": 1741105804000
    }
  },
  {
    "timestamp": "2025-03-04T16:32:00.000Z",
    "metadata": {
      "deviceId": "device-123",
      "data": 0,
      "timestamp": 1741105920000
    }
  },
  {
    "timestamp": "2025-03-04T16:33:28.000Z",
    "metadata": {
      "deviceId": "device-123",
      "data": 1,
      "timestamp": 1741106008000
    }
  },
  {
    "timestamp": "2025-03-04T16:34:58.000Z",
    "metadata": {
      "deviceId": "device-123",
      "data": 0,
      "timestamp": 1741106098000
    }
  },
  {
    "timestamp": "2025-03-04T16:36:56.000Z",
    "metadata": {
      "deviceId": "device-123",
      "data": 0,
      "timestamp": 1741106216000
    }
  },
  {
    "timestamp": "2025-03-04T16:38:36.000Z",
    "metadata": {
      "deviceId": "device-123",
      "data": 0,
      "timestamp": 1741106316000
    }
  },
  {
    "timestamp": "2025-03-04T16:39:58.000Z",
    "metadata": {
      "deviceId": "device-123",
      "data": 0,
      "timestamp": 1741106398000
    }
  },
  {
    "timestamp": "2025-03-04T16:41:55.000Z",
    "metadata": {
      "deviceId": "device-123",
      "data": 0,
      "timestamp": 1741106515000
    }
  },
  {
    "timestamp": "2025-03-04T16:43:16.000Z",
    "metadata": {
      "deviceId": "device-123",
      "data": 0,
      "timestamp": 1741106596000
    }
  },
  {
    "timestamp": "2025-03-04T16:44:49.000Z",
    "metadata": {
      "deviceId": "device-123",
      "data": 1,
      "timestamp": 1741106689000
    }
  },
  {
    "timestamp": "2025-03-04T16:45:50.000Z",
    "metadata": {
      "deviceId": "device-123",
      "data": 0,
      "timestamp": 1741106750000
    }
  },
  {
    "timestamp": "2025-03-04T16:46:58.000Z",
    "metadata": {
      "deviceId": "device-123",
      "data": 1,
      "timestamp": 1741106818000
    }
  },
  {
    "timestamp": "2025-03-04T16:48:40.000Z",
    "metadata": {
      "deviceId": "device-123",
      "data": 0,
      "timestamp": 1741106920000
    }
  },
  {
    "timestamp": "2025-03-04T16:50:25.000Z",
    "metadata": {
      "deviceId": "device-123",
      "data": 1,
      "timestamp": 1741107025000
    }
  },
  {
    "timestamp": "2025-03-04T16:51:33.000Z",
    "metadata": {
      "deviceId": "device-123",
      "data": 0,
      "timestamp": 1741107093000
    }
  },
  {
    "timestamp": "2025-03-04T16:53:20.000Z",
    "metadata": {
      "deviceId": "device-123",
      "data": 0,
      "timestamp": 1741107200000
    }
  },
  {
    "timestamp": "2025-03-04T16:54:57.000Z",
    "metadata": {
      "deviceId": "device-123",
      "data": 0,
      "timestamp": 1741107297000
    }
  },
  {
    "timestamp": "2025-03-04T16:56:54.000Z",
    "metadata": {
      "deviceId": "device-123",
      "data": 1,
      "timestamp": 1741107414000
    }
  },
  {
    "timestamp": "2025-03-04T16:58:16.000Z",
    "metadata": {
      "deviceId": "device-123",
      "data": 1,
      "timestamp": 1741107496000
    }
  },
  {
    "timestamp": "2025-03-04T17:00:08.000Z",
    "metadata": {
      "deviceId": "device-123",
      "data": 1,
      "timestamp": 1741107608000
    }
  },
  {
    "timestamp": "2025-03-04T17:01:52.000Z",
    "metadata": {
      "deviceId": "device-123",
      "data": 0,
      "timestamp": 1741107712000
    }
  },
  {
    "timestamp": "2025-03-04T17:03:44.000Z",
    "metadata": {
      "deviceId": "device-123",
      "data": 0,
      "timestamp": 1741107824000
    }
  },
  {
    "timestamp": "2025-03-04T17:05:22.000Z",
    "metadata": {
      "deviceId": "device-123",
      "data": 1,
      "timestamp": 1741107922000
    }
  },
  {
    "timestamp": "2025-03-04T17:07:16.000Z",
    "metadata": {
      "deviceId": "device-123",
      "data": 0,
      "timestamp": 1741108036000
    }
  },
  {
    "timestamp": "2025-03-04T17:09:01.000Z",
    "metadata": {
      "deviceId": "device-123",
      "data": 1,
      "timestamp": 1741108141000
    }
  },
  {
    "timestamp": "2025-03-04T17:10:08.000Z",
    "metadata": {
      "deviceId": "device-123",
      "data": 1,
      "timestamp": 1741108208000
    }
  },
  {
    "timestamp": "2025-03-04T17:11:11.000Z",
    "metadata": {
      "deviceId": "device-123",
      "data": 0,
      "timestamp": 1741108271000
    }
  },
  {
    "timestamp": "2025-03-04T17:12:40.000Z",
    "metadata": {
      "deviceId": "device-123",
      "data": 1,
      "timestamp": 1741108360000
    }
  },
  {
    "timestamp": "2025-03-04T17:13:51.000Z",
    "metadata": {
      "deviceId": "device-123",
      "data": 1,
      "timestamp": 1741108431000
    }
  },
  {
    "timestamp": "2025-03-04T17:15:19.000Z",
    "metadata": {
      "deviceId": "device-123",
      "data": 1,
      "timestamp": 1741108519000
    }
  },
  {
    "timestamp": "2025-03-04T17:16:25.000Z",
    "metadata": {
      "deviceId": "device-123",
      "data": 1,
      "timestamp": 1741108585000
    }
  },
  {
    "timestamp": "2025-03-04T17:17:50.000Z",
    "metadata": {
      "deviceId": "device-123",
      "data": 1,
      "timestamp": 1741108670000
    }
  },
  {
    "timestamp": "2025-03-04T17:19:16.000Z",
    "metadata": {
      "deviceId": "device-123",
      "data": 1,
      "timestamp": 1741108756000
    }
  },
  {
    "timestamp": "2025-03-04T17:20:29.000Z",
    "metadata": {
      "deviceId": "device-123",
      "data": 0,
      "timestamp": 1741108829000
    }
  },
  {
    "timestamp": "2025-03-04T17:22:00.000Z",
    "metadata": {
      "deviceId": "device-123",
      "data": 1,
      "timestamp": 1741108920000
    }
  },
  {
    "timestamp": "2025-03-04T17:23:09.000Z",
    "metadata": {
      "deviceId": "device-123",
      "data": 0,
      "timestamp": 1741108989000
    }
  },
  {
    "timestamp": "2025-03-04T17:25:09.000Z",
    "metadata": {
      "deviceId": "device-123",
      "data": 1,
      "timestamp": 1741109109000
    }
  },
  {
    "timestamp": "2025-03-04T17:26:27.000Z",
    "metadata": {
      "deviceId": "device-123",
      "data": 0,
      "timestamp": 1741109187000
    }
  },
  {
    "timestamp": "2025-03-04T17:28:24.000Z",
    "metadata": {
      "deviceId": "device-123",
      "data": 0,
      "timestamp": 1741109304000
    }
  },
  {
    "timestamp": "2025-03-04T17:29:29.000Z",
    "metadata": {
      "deviceId": "device-123",
      "data": 0,
      "timestamp": 1741109369000
    }
  },
  {
    "timestamp": "2025-03-04T17:30:58.000Z",
    "metadata": {
      "deviceId": "device-123",
      "data": 1,
      "timestamp": 1741109458000
    }
  },
  {
    "timestamp": "2025-03-04T17:32:09.000Z",
    "metadata": {
      "deviceId": "device-123",
      "data": 1,
      "timestamp": 1741109529000
    }
  },
  {
    "timestamp": "2025-03-04T17:33:27.000Z",
    "metadata": {
      "deviceId": "device-123",
      "data": 0,
      "timestamp": 1741109607000
    }
  },
  {
    "timestamp": "2025-03-04T17:34:49.000Z",
    "metadata": {
      "deviceId": "device-123",
      "data": 1,
      "timestamp": 1741109689000
    }
  },
  {
    "timestamp": "2025-03-04T17:36:09.000Z",
    "metadata": {
      "deviceId": "device-123",
      "data": 0,
      "timestamp": 1741109769000
    }
  },
  {
    "timestamp": "2025-03-04T17:37:30.000Z",
    "metadata": {
      "deviceId": "device-123",
      "data": 0,
      "timestamp": 1741109850000
    }
  },
  {
    "timestamp": "2025-03-04T17:38:50.000Z",
    "metadata": {
      "deviceId": "device-123",
      "data": 0,
      "timestamp": 1741109930000
    }
  },
  {
    "timestamp": "2025-03-04T17:40:46.000Z",
    "metadata": {
      "deviceId": "device-123",
      "data": 1,
      "timestamp": 1741110046000
    }
  },
  {
    "timestamp": "2025-03-04T17:41:57.000Z",
    "metadata": {
      "deviceId": "device-123",
      "data": 0,
      "timestamp": 1741110117000
    }
  },
  {
    "timestamp": "2025-03-04T17:43:51.000Z",
    "metadata": {
      "deviceId": "device-123",
      "data": 0,
      "timestamp": 1741110231000
    }
  },
  {
    "timestamp": "2025-03-04T17:45:13.000Z",
    "metadata": {
      "deviceId": "device-123",
      "data": 1,
      "timestamp": 1741110313000
    }
  },
  {
    "timestamp": "2025-03-04T17:47:00.000Z",
    "metadata": {
      "deviceId": "device-123",
      "data": 0,
      "timestamp": 1741110420000
    }
  },
  {
    "timestamp": "2025-03-04T17:48:32.000Z",
    "metadata": {
      "deviceId": "device-123",
      "data": 0,
      "timestamp": 1741110512000
    }
  },
  {
    "timestamp": "2025-03-04T17:49:54.000Z",
    "metadata": {
      "deviceId": "device-123",
      "data": 1,
      "timestamp": 1741110594000
    }
  },
  {
    "timestamp": "2025-03-04T17:51:34.000Z",
    "metadata": {
      "deviceId": "device-123",
      "data": 1,
      "timestamp": 1741110694000
    }
  },
  {
    "timestamp": "2025-03-04T17:53:33.000Z",
    "metadata": {
      "deviceId": "device-123",
      "data": 1,
      "timestamp": 1741110813000
    }
  },
  {
    "timestamp": "2025-03-04T17:55:12.000Z",
    "metadata": {
      "deviceId": "device-123",
      "data": 1,
      "timestamp": 1741110912000
    }
  },
  {
    "timestamp": "2025-03-04T17:56:36.000Z",
    "metadata": {
      "deviceId": "device-123",
      "data": 1,
      "timestamp": 1741110996000
    }
  },
  {
    "timestamp": "2025-03-04T17:58:08.000Z",
    "metadata": {
      "deviceId": "device-123",
      "data": 1,
      "timestamp": 1741111088000
    }
  },
  {
    "timestamp": "2025-03-04T17:59:22.000Z",
    "metadata": {
      "deviceId": "device-123",
      "data": 0,
      "timestamp": 1741111162000
    }
  },
  {
    "timestamp": "2025-03-04T18:00:32.000Z",
    "metadata": {
      "deviceId": "device-123",
      "data": 0,
      "timestamp": 1741111232000
    }
  },
  {
    "timestamp": "2025-03-04T18:01:32.000Z",
    "metadata": {
      "deviceId": "device-123",
      "data": 0,
      "timestamp": 1741111292000
    }
  },
  {
    "timestamp": "2025-03-04T18:03:04.000Z",
    "metadata": {
      "deviceId": "device-123",
      "data": 0,
      "timestamp": 1741111384000
    }
  },
  {
    "timestamp": "2025-03-04T18:04:12.000Z",
    "metadata": {
      "deviceId": "device-123",
      "data": 0,
      "timestamp": 1741111452000
    }
  },
  {
    "timestamp": "2025-03-04T18:05:43.000Z",
    "metadata": {
      "deviceId": "device-123",
      "data": 1,
      "timestamp": 1741111543000
    }
  },
  {
    "timestamp": "2025-03-04T18:07:09.000Z",
    "metadata": {
      "deviceId": "device-123",
      "data": 0,
      "timestamp": 1741111629000
    }
  },
  {
    "timestamp": "2025-03-04T18:08:24.000Z",
    "metadata": {
      "deviceId": "device-123",
      "data": 0,
      "timestamp": 1741111704000
    }
  },
  {
    "timestamp": "2025-03-04T18:09:26.000Z",
    "metadata": {
      "deviceId": "device-123",
      "data": 0,
      "timestamp": 1741111766000
    }
  },
  {
    "timestamp": "2025-03-04T18:10:43.000Z",
    "metadata": {
      "deviceId": "device-123",
      "data": 1,
      "timestamp": 1741111843000
    }
  },
  {
    "timestamp": "2025-03-04T18:11:58.000Z",
    "metadata": {
      "deviceId": "device-123",
      "data": 0,
      "timestamp": 1741111918000
    }
  },
  {
    "timestamp": "2025-03-04T18:13:45.000Z",
    "metadata": {
      "deviceId": "device-123",
      "data": 0,
      "timestamp": 1741112025000
    }
  },
  {
    "timestamp": "2025-03-04T18:14:48.000Z",
    "metadata": {
      "deviceId": "device-123",
      "data": 0,
      "timestamp": 1741112088000
    }
  },
  {
    "timestamp": "2025-03-04T18:16:40.000Z",
    "metadata": {
      "deviceId": "device-123",
      "data": 1,
      "timestamp": 1741112200000
    }
  },
  {
    "timestamp": "2025-03-04T18:18:23.000Z",
    "metadata": {
      "deviceId": "device-123",
      "data": 1,
      "timestamp": 1741112303000
    }
  },
  {
    "timestamp": "2025-03-04T18:19:55.000Z",
    "metadata": {
      "deviceId": "device-123",
      "data": 0,
      "timestamp": 1741112395000
    }
  },
  {
    "timestamp": "2025-03-04T18:21:06.000Z",
    "metadata": {
      "deviceId": "device-123",
      "data": 1,
      "timestamp": 1741112466000
    }
  },
  {
    "timestamp": "2025-03-04T18:22:26.000Z",
    "metadata": {
      "deviceId": "device-123",
      "data": 0,
      "timestamp": 1741112546000
    }
  },
  {
    "timestamp": "2025-03-04T18:24:25.000Z",
    "metadata": {
      "deviceId": "device-123",
      "data": 0,
      "timestamp": 1741112665000
    }
  },
  {
    "timestamp": "2025-03-04T18:25:30.000Z",
    "metadata": {
      "deviceId": "device-123",
      "data": 0,
      "timestamp": 1741112730000
    }
  },
  {
    "timestamp": "2025-03-04T18:26:58.000Z",
    "metadata": {
      "deviceId": "device-123",
      "data": 1,
      "timestamp": 1741112818000
    }
  },
  {
    "timestamp": "2025-03-04T18:28:35.000Z",
    "metadata": {
      "deviceId": "device-123",
      "data": 0,
      "timestamp": 1741112915000
    }
  },
  {
    "timestamp": "2025-03-04T18:30:03.000Z",
    "metadata": {
      "deviceId": "device-123",
      "data": 1,
      "timestamp": 1741113003000
    }
  },
  {
    "timestamp": "2025-03-04T18:31:35.000Z",
    "metadata": {
      "deviceId": "device-123",
      "data": 0,
      "timestamp": 1741113095000
    }
  },
  {
    "timestamp": "2025-03-04T18:32:42.000Z",
    "metadata": {
      "deviceId": "device-123",
      "data": 1,
      "timestamp": 1741113162000
    }
  },
  {
    "timestamp": "2025-03-04T18:34:12.000Z",
    "metadata": {
      "deviceId": "device-123",
      "data": 1,
      "timestamp": 1741113252000
    }
  },
  {
    "timestamp": "2025-03-04T18:35:58.000Z",
    "metadata": {
      "deviceId": "device-123",
      "data": 1,
      "timestamp": 1741113358000
    }
  },
  {
    "timestamp": "2025-03-04T18:37:38.000Z",
    "metadata": {
      "deviceId": "device-123",
      "data": 1,
      "timestamp": 1741113458000
    }
  },
  {
    "timestamp": "2025-03-04T18:38:54.000Z",
    "metadata": {
      "deviceId": "device-123",
      "data": 0,
      "timestamp": 1741113534000
    }
  },
  {
    "timestamp": "2025-03-04T18:40:28.000Z",
    "metadata": {
      "deviceId": "device-123",
      "data": 0,
      "timestamp": 1741113628000
    }
  },
  {
    "timestamp": "2025-03-04T18:42:18.000Z",
    "metadata": {
      "deviceId": "device-123",
      "data": 1,
      "timestamp": 1741113738000
    }
  },
  {
    "timestamp": "2025-03-04T18:43:48.000Z",
    "metadata": {
      "deviceId": "device-123",
      "data": 1,
      "timestamp": 1741113828000
    }
  },
  {
    "timestamp": "2025-03-04T18:44:53.000Z",
    "metadata": {
      "deviceId": "device-123",
      "data": 1,
      "timestamp": 1741113893000
    }
  },
  {
    "timestamp": "2025-03-04T18:46:14.000Z",
    "metadata": {
      "deviceId": "device-123",
      "data": 0,
      "timestamp": 1741113974000
    }
  },
  {
    "timestamp": "2025-03-04T18:48:08.000Z",
    "metadata": {
      "deviceId": "device-123",
      "data": 0,
      "timestamp": 1741114088000
    }
  },
  {
    "timestamp": "2025-03-04T18:49:30.000Z",
    "metadata": {
      "deviceId": "device-123",
      "data": 1,
      "timestamp": 1741114170000
    }
  },
  {
    "timestamp": "2025-03-04T18:51:22.000Z",
    "metadata": {
      "deviceId": "device-123",
      "data": 1,
      "timestamp": 1741114282000
    }
  },
  {
    "timestamp": "2025-03-04T18:52:35.000Z",
    "metadata": {
      "deviceId": "device-123",
      "data": 0,
      "timestamp": 1741114355000
    }
  },
  {
    "timestamp": "2025-03-04T18:53:42.000Z",
    "metadata": {
      "deviceId": "device-123",
      "data": 0,
      "timestamp": 1741114422000
    }
  },
  {
    "timestamp": "2025-03-04T18:55:03.000Z",
    "metadata": {
      "deviceId": "device-123",
      "data": 0,
      "timestamp": 1741114503000
    }
  },
  {
    "timestamp": "2025-03-04T18:56:56.000Z",
    "metadata": {
      "deviceId": "device-123",
      "data": 0,
      "timestamp": 1741114616000
    }
  },
  {
    "timestamp": "2025-03-04T18:58:18.000Z",
    "metadata": {
      "deviceId": "device-123",
      "data": 1,
      "timestamp": 1741114698000
    }
  },
  {
    "timestamp": "2025-03-04T19:00:00.000Z",
    "metadata": {
      "deviceId": "device-123",
      "data": 1,
      "timestamp": 1741114800000
    }
  },
  {
    "timestamp": "2025-03-04T19:01:17.000Z",
    "metadata": {
      "deviceId": "device-123",
      "data": 1,
      "timestamp": 1741114877000
    }
  },
  {
    "timestamp": "2025-03-04T19:02:39.000Z",
    "metadata": {
      "deviceId": "device-123",
      "data": 0,
      "timestamp": 1741114959000
    }
  },
  {
    "timestamp": "2025-03-04T19:03:49.000Z",
    "metadata": {
      "deviceId": "device-123",
      "data": 0,
      "timestamp": 1741115029000
    }
  },
  {
    "timestamp": "2025-03-04T19:04:56.000Z",
    "metadata": {
      "deviceId": "device-123",
      "data": 1,
      "timestamp": 1741115096000
    }
  },
  {
    "timestamp": "2025-03-04T19:06:16.000Z",
    "metadata": {
      "deviceId": "device-123",
      "data": 0,
      "timestamp": 1741115176000
    }
  },
  {
    "timestamp": "2025-03-04T19:08:09.000Z",
    "metadata": {
      "deviceId": "device-123",
      "data": 1,
      "timestamp": 1741115289000
    }
  },
  {
    "timestamp": "2025-03-04T19:09:58.000Z",
    "metadata": {
      "deviceId": "device-123",
      "data": 0,
      "timestamp": 1741115398000
    }
  },
  {
    "timestamp": "2025-03-04T19:11:22.000Z",
    "metadata": {
      "deviceId": "device-123",
      "data": 1,
      "timestamp": 1741115482000
    }
  },
  {
    "timestamp": "2025-03-04T19:13:02.000Z",
    "metadata": {
      "deviceId": "device-123",
      "data": 0,
      "timestamp": 1741115582000
    }
  },
  {
    "timestamp": "2025-03-04T19:14:22.000Z",
    "metadata": {
      "deviceId": "device-123",
      "data": 0,
      "timestamp": 1741115662000
    }
  },
  {
    "timestamp": "2025-03-04T19:15:34.000Z",
    "metadata": {
      "deviceId": "device-123",
      "data": 1,
      "timestamp": 1741115734000
    }
  },
  {
    "timestamp": "2025-03-04T19:17:31.000Z",
    "metadata": {
      "deviceId": "device-123",
      "data": 1,
      "timestamp": 1741115851000
    }
  },
  {
    "timestamp": "2025-03-04T19:19:08.000Z",
    "metadata": {
      "deviceId": "device-123",
      "data": 0,
      "timestamp": 1741115948000
    }
  },
  {
    "timestamp": "2025-03-04T19:20:25.000Z",
    "metadata": {
      "deviceId": "device-123",
      "data": 0,
      "timestamp": 1741116025000
    }
  },
  {
    "timestamp": "2025-03-04T19:22:17.000Z",
    "metadata": {
      "deviceId": "device-123",
      "data": 0,
      "timestamp": 1741116137000
    }
  },
  {
    "timestamp": "2025-03-04T19:23:26.000Z",
    "metadata": {
      "deviceId": "device-123",
      "data": 0,
      "timestamp": 1741116206000
    }
  },
  {
    "timestamp": "2025-03-04T19:25:12.000Z",
    "metadata": {
      "deviceId": "device-123",
      "data": 1,
      "timestamp": 1741116312000
    }
  },
  {
    "timestamp": "2025-03-04T19:26:24.000Z",
    "metadata": {
      "deviceId": "device-123",
      "data": 1,
      "timestamp": 1741116384000
    }
  },
  {
    "timestamp": "2025-03-04T19:28:10.000Z",
    "metadata": {
      "deviceId": "device-123",
      "data": 1,
      "timestamp": 1741116490000
    }
  },
  {
    "timestamp": "2025-03-04T19:29:18.000Z",
    "metadata": {
      "deviceId": "device-123",
      "data": 1,
      "timestamp": 1741116558000
    }
  },
  {
    "timestamp": "2025-03-04T19:30:41.000Z",
    "metadata": {
      "deviceId": "device-123",
      "data": 0,
      "timestamp": 1741116641000
    }
  },
  {
    "timestamp": "2025-03-04T19:32:23.000Z",
    "metadata": {
      "deviceId": "device-123",
      "data": 1,
      "timestamp": 1741116743000
    }
  },
  {
    "timestamp": "2025-03-04T19:33:59.000Z",
    "metadata": {
      "deviceId": "device-123",
      "data": 0,
      "timestamp": 1741116839000
    }
  },
  {
    "timestamp": "2025-03-04T19:35:32.000Z",
    "metadata": {
      "deviceId": "device-123",
      "data": 1,
      "timestamp": 1741116932000
    }
  },
  {
    "timestamp": "2025-03-04T19:36:41.000Z",
    "metadata": {
      "deviceId": "device-123",
      "data": 0,
      "timestamp": 1741117001000
    }
  },
  {
    "timestamp": "2025-03-04T19:38:19.000Z",
    "metadata": {
      "deviceId": "device-123",
      "data": 1,
      "timestamp": 1741117099000
    }
  },
  {
    "timestamp": "2025-03-04T19:40:13.000Z",
    "metadata": {
      "deviceId": "device-123",
      "data": 0,
      "timestamp": 1741117213000
    }
  },
  {
    "timestamp": "2025-03-04T19:42:10.000Z",
    "metadata": {
      "deviceId": "device-123",
      "data": 0,
      "timestamp": 1741117330000
    }
  },
  {
    "timestamp": "2025-03-04T19:43:52.000Z",
    "metadata": {
      "deviceId": "device-123",
      "data": 0,
      "timestamp": 1741117432000
    }
  },
  {
    "timestamp": "2025-03-04T19:45:42.000Z",
    "metadata": {
      "deviceId": "device-123",
      "data": 0,
      "timestamp": 1741117542000
    }
  },
  {
    "timestamp": "2025-03-04T19:46:54.000Z",
    "metadata": {
      "deviceId": "device-123",
      "data": 0,
      "timestamp": 1741117614000
    }
  },
  {
    "timestamp": "2025-03-04T19:48:15.000Z",
    "metadata": {
      "deviceId": "device-123",
      "data": 1,
      "timestamp": 1741117695000
    }
  },
  {
    "timestamp": "2025-03-04T19:50:12.000Z",
    "metadata": {
      "deviceId": "device-123",
      "data": 0,
      "timestamp": 1741117812000
    }
  },
  {
    "timestamp": "2025-03-04T19:51:54.000Z",
    "metadata": {
      "deviceId": "device-123",
      "data": 0,
      "timestamp": 1741117914000
    }
  },
  {
    "timestamp": "2025-03-04T19:52:55.000Z",
    "metadata": {
      "deviceId": "device-123",
      "data": 0,
      "timestamp": 1741117975000
    }
  },
  {
    "timestamp": "2025-03-04T19:54:49.000Z",
    "metadata": {
      "deviceId": "device-123",
      "data": 1,
      "timestamp": 1741118089000
    }
  },
  {
    "timestamp": "2025-03-04T19:55:50.000Z",
    "metadata": {
      "deviceId": "device-123",
      "data": 1,
      "timestamp": 1741118150000
    }
  },
  {
    "timestamp": "2025-03-04T19:57:25.000Z",
    "metadata": {
      "deviceId": "device-123",
      "data": 0,
      "timestamp": 1741118245000
    }
  },
  {
    "timestamp": "2025-03-04T19:58:59.000Z",
    "metadata": {
      "deviceId": "device-123",
      "data": 0,
      "timestamp": 1741118339000
    }
  },
  {
    "timestamp": "2025-03-04T20:00:12.000Z",
    "metadata": {
      "deviceId": "device-123",
      "data": 0,
      "timestamp": 1741118412000
    }
  },
  {
    "timestamp": "2025-03-04T20:02:09.000Z",
    "metadata": {
      "deviceId": "device-123",
      "data": 1,
      "timestamp": 1741118529000
    }
  },
  {
    "timestamp": "2025-03-04T20:03:09.000Z",
    "metadata": {
      "deviceId": "device-123",
      "data": 0,
      "timestamp": 1741118589000
    }
  },
  {
    "timestamp": "2025-03-04T20:04:34.000Z",
    "metadata": {
      "deviceId": "device-123",
      "data": 0,
      "timestamp": 1741118674000
    }
  },
  {
    "timestamp": "2025-03-04T20:06:13.000Z",
    "metadata": {
      "deviceId": "device-123",
      "data": 0,
      "timestamp": 1741118773000
    }
  },
  {
    "timestamp": "2025-03-04T20:07:51.000Z",
    "metadata": {
      "deviceId": "device-123",
      "data": 1,
      "timestamp": 1741118871000
    }
  },
  {
    "timestamp": "2025-03-04T20:09:03.000Z",
    "metadata": {
      "deviceId": "device-123",
      "data": 1,
      "timestamp": 1741118943000
    }
  },
  {
    "timestamp": "2025-03-04T20:10:47.000Z",
    "metadata": {
      "deviceId": "device-123",
      "data": 0,
      "timestamp": 1741119047000
    }
  },
  {
    "timestamp": "2025-03-04T20:12:33.000Z",
    "metadata": {
      "deviceId": "device-123",
      "data": 0,
      "timestamp": 1741119153000
    }
  },
  {
    "timestamp": "2025-03-04T20:13:41.000Z",
    "metadata": {
      "deviceId": "device-123",
      "data": 1,
      "timestamp": 1741119221000
    }
  },
  {
    "timestamp": "2025-03-04T20:15:40.000Z",
    "metadata": {
      "deviceId": "device-123",
      "data": 0,
      "timestamp": 1741119340000
    }
  },
  {
    "timestamp": "2025-03-04T20:17:09.000Z",
    "metadata": {
      "deviceId": "device-123",
      "data": 1,
      "timestamp": 1741119429000
    }
  },
  {
    "timestamp": "2025-03-04T20:18:26.000Z",
    "metadata": {
      "deviceId": "device-123",
      "data": 0,
      "timestamp": 1741119506000
    }
  },
  {
    "timestamp": "2025-03-04T20:19:42.000Z",
    "metadata": {
      "deviceId": "device-123",
      "data": 1,
      "timestamp": 1741119582000
    }
  },
  {
    "timestamp": "2025-03-04T20:21:08.000Z",
    "metadata": {
      "deviceId": "device-123",
      "data": 1,
      "timestamp": 1741119668000
    }
  },
  {
    "timestamp": "2025-03-04T20:22:32.000Z",
    "metadata": {
      "deviceId": "device-123",
      "data": 1,
      "timestamp": 1741119752000
    }
  },
  {
    "timestamp": "2025-03-04T20:24:01.000Z",
    "metadata": {
      "deviceId": "device-123",
      "data": 1,
      "timestamp": 1741119841000
    }
  },
  {
    "timestamp": "2025-03-04T20:25:58.000Z",
    "metadata": {
      "deviceId": "device-123",
      "data": 0,
      "timestamp": 1741119958000
    }
  },
  {
    "timestamp": "2025-03-04T20:27:49.000Z",
    "metadata": {
      "deviceId": "device-123",
      "data": 1,
      "timestamp": 1741120069000
    }
  },
  {
    "timestamp": "2025-03-04T20:28:50.000Z",
    "metadata": {
      "deviceId": "device-123",
      "data": 0,
      "timestamp": 1741120130000
    }
  },
  {
    "timestamp": "2025-03-04T20:30:22.000Z",
    "metadata": {
      "deviceId": "device-123",
      "data": 0,
      "timestamp": 1741120222000
    }
  },
  {
    "timestamp": "2025-03-04T20:31:27.000Z",
    "metadata": {
      "deviceId": "device-123",
      "data": 1,
      "timestamp": 1741120287000
    }
  },
  {
    "timestamp": "2025-03-04T20:32:42.000Z",
    "metadata": {
      "deviceId": "device-123",
      "data": 1,
      "timestamp": 1741120362000
    }
  },
  {
    "timestamp": "2025-03-04T20:34:42.000Z",
    "metadata": {
      "deviceId": "device-123",
      "data": 0,
      "timestamp": 1741120482000
    }
  },
  {
    "timestamp": "2025-03-04T20:35:53.000Z",
    "metadata": {
      "deviceId": "device-123",
      "data": 1,
      "timestamp": 1741120553000
    }
  },
  {
    "timestamp": "2025-03-04T20:37:42.000Z",
    "metadata": {
      "deviceId": "device-123",
      "data": 0,
      "timestamp": 1741120662000
    }
  },
  {
    "timestamp": "2025-03-04T20:38:46.000Z",
    "metadata": {
      "deviceId": "device-123",
      "data": 1,
      "timestamp": 1741120726000
    }
  },
  {
    "timestamp": "2025-03-04T20:39:58.000Z",
    "metadata": {
      "deviceId": "device-123",
      "data": 1,
      "timestamp": 1741120798000
    }
  },
  {
    "timestamp": "2025-03-04T20:41:53.000Z",
    "metadata": {
      "deviceId": "device-123",
      "data": 1,
      "timestamp": 1741120913000
    }
  },
  {
    "timestamp": "2025-03-04T20:43:00.000Z",
    "metadata": {
      "deviceId": "device-123",
      "data": 1,
      "timestamp": 1741120980000
    }
  },
  {
    "timestamp": "2025-03-04T20:44:33.000Z",
    "metadata": {
      "deviceId": "device-123",
      "data": 1,
      "timestamp": 1741121073000
    }
  },
  {
    "timestamp": "2025-03-04T20:46:19.000Z",
    "metadata": {
      "deviceId": "device-123",
      "data": 1,
      "timestamp": 1741121179000
    }
  },
  {
    "timestamp": "2025-03-04T20:47:37.000Z",
    "metadata": {
      "deviceId": "device-123",
      "data": 1,
      "timestamp": 1741121257000
    }
  },
  {
    "timestamp": "2025-03-04T20:49:27.000Z",
    "metadata": {
      "deviceId": "device-123",
      "data": 1,
      "timestamp": 1741121367000
    }
  },
  {
    "timestamp": "2025-03-04T20:50:36.000Z",
    "metadata": {
      "deviceId": "device-123",
      "data": 0,
      "timestamp": 1741121436000
    }
  },
  {
    "timestamp": "2025-03-04T20:52:35.000Z",
    "metadata": {
      "deviceId": "device-123",
      "data": 0,
      "timestamp": 1741121555000
    }
  },
  {
    "timestamp": "2025-03-04T20:54:14.000Z",
    "metadata": {
      "deviceId": "device-123",
      "data": 1,
      "timestamp": 1741121654000
    }
  },
  {
    "timestamp": "2025-03-04T20:55:23.000Z",
    "metadata": {
      "deviceId": "device-123",
      "data": 1,
      "timestamp": 1741121723000
    }
  },
  {
    "timestamp": "2025-03-04T20:57:08.000Z",
    "metadata": {
      "deviceId": "device-123",
      "data": 0,
      "timestamp": 1741121828000
    }
  },
  {
    "timestamp": "2025-03-04T20:58:20.000Z",
    "metadata": {
      "deviceId": "device-123",
      "data": 0,
      "timestamp": 1741121900000
    }
  },
  {
    "timestamp": "2025-03-04T20:59:40.000Z",
    "metadata": {
      "deviceId": "device-123",
      "data": 1,
      "timestamp": 1741121980000
    }
  },
  {
    "timestamp": "2025-03-04T21:01:37.000Z",
    "metadata": {
      "deviceId": "device-123",
      "data": 1,
      "timestamp": 1741122097000
    }
  },
  {
    "timestamp": "2025-03-04T21:03:20.000Z",
    "metadata": {
      "deviceId": "device-123",
      "data": 0,
      "timestamp": 1741122200000
    }
  },
  {
    "timestamp": "2025-03-04T21:05:01.000Z",
    "metadata": {
      "deviceId": "device-123",
      "data": 0,
      "timestamp": 1741122301000
    }
  },
  {
    "timestamp": "2025-03-04T21:06:52.000Z",
    "metadata": {
      "deviceId": "device-123",
      "data": 0,
      "timestamp": 1741122412000
    }
  },
  {
    "timestamp": "2025-03-04T21:08:29.000Z",
    "metadata": {
      "deviceId": "device-123",
      "data": 1,
      "timestamp": 1741122509000
    }
  },
  {
    "timestamp": "2025-03-04T21:09:56.000Z",
    "metadata": {
      "deviceId": "device-123",
      "data": 1,
      "timestamp": 1741122596000
    }
  },
  {
    "timestamp": "2025-03-04T21:11:54.000Z",
    "metadata": {
      "deviceId": "device-123",
      "data": 0,
      "timestamp": 1741122714000
    }
  },
  {
    "timestamp": "2025-03-04T21:13:16.000Z",
    "metadata": {
      "deviceId": "device-123",
      "data": 1,
      "timestamp": 1741122796000
    }
  },
  {
    "timestamp": "2025-03-04T21:14:57.000Z",
    "metadata": {
      "deviceId": "device-123",
      "data": 1,
      "timestamp": 1741122897000
    }
  },
  {
    "timestamp": "2025-03-04T21:16:01.000Z",
    "metadata": {
      "deviceId": "device-123",
      "data": 0,
      "timestamp": 1741122961000
    }
  },
  {
    "timestamp": "2025-03-04T21:17:32.000Z",
    "metadata": {
      "deviceId": "device-123",
      "data": 1,
      "timestamp": 1741123052000
    }
  },
  {
    "timestamp": "2025-03-04T21:19:30.000Z",
    "metadata": {
      "deviceId": "device-123",
      "data": 1,
      "timestamp": 1741123170000
    }
  },
  {
    "timestamp": "2025-03-04T21:20:56.000Z",
    "metadata": {
      "deviceId": "device-123",
      "data": 1,
      "timestamp": 1741123256000
    }
  },
  {
    "timestamp": "2025-03-04T21:22:22.000Z",
    "metadata": {
      "deviceId": "device-123",
      "data": 0,
      "timestamp": 1741123342000
    }
  },
  {
    "timestamp": "2025-03-04T21:23:59.000Z",
    "metadata": {
      "deviceId": "device-123",
      "data": 0,
      "timestamp": 1741123439000
    }
  },
  {
    "timestamp": "2025-03-04T21:25:11.000Z",
    "metadata": {
      "deviceId": "device-123",
      "data": 1,
      "timestamp": 1741123511000
    }
  },
  {
    "timestamp": "2025-03-04T21:26:38.000Z",
    "metadata": {
      "deviceId": "device-123",
      "data": 1,
      "timestamp": 1741123598000
    }
  },
  {
    "timestamp": "2025-03-04T21:28:05.000Z",
    "metadata": {
      "deviceId": "device-123",
      "data": 1,
      "timestamp": 1741123685000
    }
  },
  {
    "timestamp": "2025-03-04T21:29:53.000Z",
    "metadata": {
      "deviceId": "device-123",
      "data": 0,
      "timestamp": 1741123793000
    }
  },
  {
    "timestamp": "2025-03-04T21:31:31.000Z",
    "metadata": {
      "deviceId": "device-123",
      "data": 0,
      "timestamp": 1741123891000
    }
  },
  {
    "timestamp": "2025-03-04T21:32:45.000Z",
    "metadata": {
      "deviceId": "device-123",
      "data": 1,
      "timestamp": 1741123965000
    }
  },
  {
    "timestamp": "2025-03-04T21:34:14.000Z",
    "metadata": {
      "deviceId": "device-123",
      "data": 1,
      "timestamp": 1741124054000
    }
  },
  {
    "timestamp": "2025-03-04T21:35:59.000Z",
    "metadata": {
      "deviceId": "device-123",
      "data": 0,
      "timestamp": 1741124159000
    }
  },
  {
    "timestamp": "2025-03-04T21:37:04.000Z",
    "metadata": {
      "deviceId": "device-123",
      "data": 1,
      "timestamp": 1741124224000
    }
  },
  {
    "timestamp": "2025-03-04T21:38:06.000Z",
    "metadata": {
      "deviceId": "device-123",
      "data": 0,
      "timestamp": 1741124286000
    }
  },
  {
    "timestamp": "2025-03-04T21:39:38.000Z",
    "metadata": {
      "deviceId": "device-123",
      "data": 0,
      "timestamp": 1741124378000
    }
  },
  {
    "timestamp": "2025-03-04T21:41:12.000Z",
    "metadata": {
      "deviceId": "device-123",
      "data": 0,
      "timestamp": 1741124472000
    }
  },
  {
    "timestamp": "2025-03-04T21:42:50.000Z",
    "metadata": {
      "deviceId": "device-123",
      "data": 1,
      "timestamp": 1741124570000
    }
  },
  {
    "timestamp": "2025-03-04T21:44:34.000Z",
    "metadata": {
      "deviceId": "device-123",
      "data": 1,
      "timestamp": 1741124674000
    }
  },
  {
    "timestamp": "2025-03-04T21:45:52.000Z",
    "metadata": {
      "deviceId": "device-123",
      "data": 1,
      "timestamp": 1741124752000
    }
  },
  {
    "timestamp": "2025-03-04T21:47:22.000Z",
    "metadata": {
      "deviceId": "device-123",
      "data": 0,
      "timestamp": 1741124842000
    }
  },
  {
    "timestamp": "2025-03-04T21:48:49.000Z",
    "metadata": {
      "deviceId": "device-123",
      "data": 0,
      "timestamp": 1741124929000
    }
  },
  {
    "timestamp": "2025-03-04T21:50:41.000Z",
    "metadata": {
      "deviceId": "device-123",
      "data": 1,
      "timestamp": 1741125041000
    }
  },
  {
    "timestamp": "2025-03-04T21:52:32.000Z",
    "metadata": {
      "deviceId": "device-123",
      "data": 0,
      "timestamp": 1741125152000
    }
  },
  {
    "timestamp": "2025-03-04T21:54:17.000Z",
    "metadata": {
      "deviceId": "device-123",
      "data": 0,
      "timestamp": 1741125257000
    }
  },
  {
    "timestamp": "2025-03-04T21:55:25.000Z",
    "metadata": {
      "deviceId": "device-123",
      "data": 1,
      "timestamp": 1741125325000
    }
  },
  {
    "timestamp": "2025-03-04T21:56:36.000Z",
    "metadata": {
      "deviceId": "device-123",
      "data": 0,
      "timestamp": 1741125396000
    }
  },
  {
    "timestamp": "2025-03-04T21:58:02.000Z",
    "metadata": {
      "deviceId": "device-123",
      "data": 0,
      "timestamp": 1741125482000
    }
  },
  {
    "timestamp": "2025-03-04T21:59:19.000Z",
    "metadata": {
      "deviceId": "device-123",
      "data": 0,
      "timestamp": 1741125559000
    }
  }
]